Workbook
Name _27_Year: #REF!
Name _27_Year: #REF!
Name _27_Year: #REF!
Name Accounting_Method: #REF!
Name Accounting_Method: Definitions!#REF!
Name Building_Use: #REF!
Name Building_Use: Definitions!#REF!
Name Business_Activity_Code: #REF!
Name Business_Activity_Code: #REF!
Name Business_Activity_Code: Definitions!#REF!
Name Construction_Class: #REF!
Name Construction_Class: #REF!
Name Construction_Class: Definitions!#REF!
Name Occupancy_Type: #REF!
Name Occupancy_Type: #REF!
Name Occupancy_Type: Definitions!#REF!
Name Roofing: #REF!
Name Roofing: #REF!
Name Roofing: Definitions!#REF!
Name Siding: #REF!
Name Siding: Definitions!#REF!
Name Trade_Business: #REF!
Name Trade_Business: Definitions!#REF!
Name Year_No.: _275_Year
Name Year_No.: _275_Year
Name Year_No.: _275_Year
Name Year_No.: _275_Year
Name Year_No.: _275_Year
Name Yes_No: #REF!
Name Yes_No: Definitions!#REF!

Sheet Study Data
A1: Study Meta Data
A2: Property Address | B2: ='Client Summary'!G12 -> 861 E 800 S, Salt Lake City, UT 84102
A4: Analysis Date | B4: =DATE(B5,12,31) -> 46022 | D4: Basis (excluding land value) | E4: ='Client Summary'!$G$18 -> 0
A5: Study Tax Year | B5: ='Client Summary'!N13 -> 2025 | D5: ="Accumulated Depreciation as of 12/31/"&$B$5-1 -> Accumulated Depreciation as of 12/31/2024 | E5: ='Client Summary'!G19 -> 0
A6: Date Placed in Service | B6: ='Client Summary'!$G$13 -> 45292 | D6: Building Use | E6: =_xlfn.XLOOKUP('Client Summary'!$G$21,Definitions!$E$2:$E$35,Definitions!$F$2:$F$35,0,0,1) -> Single Family Residence
D9: Post Modeling Calculation | G9: Per Modeling Calculation
A10: Asset ID | B10: Property Description | C10: Date Acquired | D10: Original Basis | E10: Life (years) | F10: Estimate Input | G10: Reclassified Basis | H10: Life | I10: Method | J10: Conv | K10: ="Revised Depreciation for the Year ending 12/31/"&$B$5-1 -> Revised Depreciation for the Year ending 12/31/2024
A11: 1 | B11: Building | C11: =$B$6 -> 45292 | D11: =$E$4 -> 0 | E11: ='Client Summary'!G26 -> 27.5 | F11: =1-SUM(F12:F14) -> 0.8 | G11: =IF('Client Summary'!F26=0,'Study Data'!$D$15*'Study Data'!F11,'Client Summary'!F26) -> 0 | H11: =E11 -> 27.5 | I11: SL | J11: Mid-Month | K11: =IF($E$11=27.5,VLOOKUP($B$5-1,_27.5_Year_Post_CS[[#All],[Year]:[Cumulative Depreciation]],5),VLOOKUP($B$5-1,_39_Year_Post_CS12[[#All],[Year]:[Cumulative Depreciation]],5)) -> 0
A12: 1.1 | B12: Asset Class 57.0 - Distributive Trades and Services | C12: =$B$6 -> 45292 | D12: 0 | E12: 5 | F12: =_xlfn.XLOOKUP('Client Summary'!$G$21,Definitions!$E$2:$E$44,Definitions!$G$2:$G$44,0,0,1) -> 0.12 | G12: =IF('Client Summary'!F27=0,'Study Data'!$D$15*'Study Data'!F12,'Client Summary'!F27) -> 0 | H12: 5 | I12: 200DB | J12: Half-Year | K12: =VLOOKUP($B$5-1,_5_Year_Post_CS[[#All],[Year]:[Cumulative Depreciation]],5) -> 0
A13: 1.2 | B13: Asset Class 0.11 - Office Furniture, Fixtures and Equipment | C13: =$B$6 -> 45292 | D13: 0 | E13: 7 | F13: 0 | G13: =IF('Client Summary'!F28=0,'Study Data'!$D$15*'Study Data'!F13,'Client Summary'!F28) -> 0 | H13: 7 | I13: 200DB | J13: Half-Year | K13: =VLOOKUP($B$5-1,_7_Year_Post_CS[[#All],[Year]:[Cumulative Depreciation]],5) -> 0
A14: 1.3 | B14: Asset Class 0.30 - Land Improvements | C14: =$B$6 -> 45292 | D14: 0 | E14: 15 | F14: =_xlfn.XLOOKUP('Client Summary'!$G$21,Definitions!$E$2:$E$44,Definitions!$H$2:$H$44,0,0,1) -> 0.08 | G14: =IF('Client Summary'!F29=0,'Study Data'!$D$15*'Study Data'!F14,'Client Summary'!F29) -> 0 | H14: 15 | I14: 150DB | J14: Half-Year | K14: =VLOOKUP($B$5-1,_15_Year_Post_CS[[#All],[Year]:[Cumulative Depreciation]],5) -> 0
B15: TOTALS | D15: =SUM(D11:D14) -> 0 | F15: =SUM(F11:F14) -> 1 | G15: =SUM(G11:G14) -> 0 | K15: =SUM(K11:K14) -> 0
A18: Building (Pre CS Study) | H18: Building (Post CS Study) | O18: Personal Property (5 Year) | V18: Personal Property (7 Year) | AC18: Land Improvements (15 Year)
A19: 27.5 Yr SL | H19: 27.5 Yr SL | O19: 5 Yr 200 DB | S19: Convention | T19: =J12 -> Half-Year | V19: 7 Yr 200 DB | Z19: Convention | AA19: =J13 -> Half-Year | AC19: 15 Yr 150 DB | AG19: Convention | AH19: =J14 -> Half-Year
A20: Year No. | B20: Year | C20: 27.5-Year Rate | D20: Original Basis | E20: Annual Depreciation | F20: Cumulative Depreciation | H20: Year No. | I20: Year | J20: 27.5-Year Rate | K20: Adj Basis | L20: Annual Depreciation | M20: Cumulative Depreciation | O20: Year No. | P20: Year | Q20: 5-Year Rate | R20: Basis | S20: Annual Depreciation | T20: Cumulative Depreciation | V20: Year No. | W20: Year | X20: 7-Year Rate | Y20: Basis | Z20: Annual Depreciation | AA20: Cumulative Depreciation | AC20: Year No. | AD20: Year | AE20: 15-Year Rate | AF20: Basis | AG20: Annual Depreciation | AH20: Cumulative Depreciation
A21: 1 | B21: =IF($B$6>0,YEAR($B$6),"") -> 2024 | C21: {=INDEX('27.5-Year'!$A$1:$M$32,MATCH(_27.5_Year_Original[[#This Row],[Year No.]],'27.5-Year'!$A:$A,0),MONTH('Study Data'!$B$6)+1)} -> 0.03485 | D21: =IF($E$11=27.5,$D$11,0) -> 0 | E21: =_27.5_Year_Original[[#This Row],[Original Basis]]*_27.5_Year_Original[[#This Row],[27.5-Year Rate]] -> 0 | F21: =E21 -> 0 | H21: 1 | I21: =IF($B$6>0,YEAR($B$6),"") -> 2024 | J21: {=INDEX('27.5-Year'!$A$1:$M$32,MATCH(_27.5_Year_Post_CS[[#This Row],[Year No.]],'27.5-Year'!$A:$A,0),MONTH('Study Data'!$B$6)+1)} -> 0.03485 | K21: =IF($E$11=27.5,$G$11,0) -> 0 | L21: =_27.5_Year_Post_CS[[#This Row],[Adj Basis]]*_27.5_Year_Post_CS[[#This Row],[27.5-Year Rate]] -> 0 | M21: =L21 -> 0 | O21: 1 | P21: =IF($B$6>0,YEAR($B$6),"") -> 2024 | Q21: 0.2 | R21: =$G$12-$Q$28 -> 0 | S21: =_5_Year_Post_CS[[#This Row],[Basis]]*_5_Year_Post_CS[[#This Row],[5-Year Rate]] -> 0 | T21: =S21+Q28 -> 0 | V21: 1 | W21: =IF($B$6>0,YEAR($B$6),"") -> 2024 | X21: 0.1429 | Y21: =$G$13-$X$30 -> 0 | Z21: =_7_Year_Post_CS[[#This Row],[Basis]]*_7_Year_Post_CS[[#This Row],[7-Year Rate]] -> 0 | AA21: =Z21+X30 -> 0 | AC21: 1 | AD21: =IF($B$6>0,YEAR($B$6),"") -> 2024 | AE21: 0.05 | AF21: =$G$14-$AE$38 -> 0 | AG21: =_15_Year_Post_CS[[#This Row],[Basis]]*_15_Year_Post_CS[[#This Row],[15-Year Rate]] -> 0 | AH21: =AG21+AE38 -> 0
A22: =A21+1 -> 2 | B22: =B21+1 -> 2025 | C22: {=INDEX('27.5-Year'!$A$1:$M$32,MATCH(_27.5_Year_Original[[#This Row],[Year No.]],'27.5-Year'!$A:$A,0),MONTH('Study Data'!$B$6)+1)} -> 0.03636 | D22: =IF($E$11=27.5,$D$11,0) -> 0 | E22: =_27.5_Year_Original[[#This Row],[Original Basis]]*_27.5_Year_Original[[#This Row],[27.5-Year Rate]] -> 0 | F22: =F21+_27.5_Year_Original[[#This Row],[Annual Depreciation]] -> 0 | H22: =H21+1 -> 2 | I22: =I21+1 -> 2025 | J22: {=INDEX('27.5-Year'!$A$1:$M$32,MATCH(_27.5_Year_Post_CS[[#This Row],[Year No.]],'27.5-Year'!$A:$A,0),MONTH('Study Data'!$B$6)+1)} -> 0.03636 | K22: =IF($E$11=27.5,$G$11,0) -> 0 | L22: =_27.5_Year_Post_CS[[#This Row],[Adj Basis]]*_27.5_Year_Post_CS[[#This Row],[27.5-Year Rate]] -> 0 | M22: =M21+_27.5_Year_Post_CS[[#This Row],[Annual Depreciation]] -> 0 | O22: =O21+1 -> 2 | P22: =P21+1 -> 2025 | Q22: 0.32 | R22: =$G$12-$Q$28 -> 0 | S22: =_5_Year_Post_CS[[#This Row],[Basis]]*_5_Year_Post_CS[[#This Row],[5-Year Rate]] -> 0 | T22: =T21+_5_Year_Post_CS[[#This Row],[Annual Depreciation]] -> 0 | V22: =V21+1 -> 2 | W22: =W21+1 -> 2025 | X22: 0.2449 | Y22: =$G$13-$X$30 -> 0 | Z22: =_7_Year_Post_CS[[#This Row],[Basis]]*_7_Year_Post_CS[[#This Row],[7-Year Rate]] -> 0 | AA22: =AA21+_7_Year_Post_CS[[#This Row],[Annual Depreciation]] -> 0 | AC22: =AC21+1 -> 2 | AD22: =AD21+1 -> 2025 | AE22: 0.095 | AF22: =$G$14-$AE$38 -> 0 | AG22: =_15_Year_Post_CS[[#This Row],[Basis]]*_15_Year_Post_CS[[#This Row],[15-Year Rate]] -> 0 | AH22: =AH21+_15_Year_Post_CS[[#This Row],[Annual Depreciation]] -> 0
A23: =A22+1 -> 3 | B23: =B22+1 -> 2026 | C23: {=INDEX('27.5-Year'!$A$1:$M$32,MATCH(_27.5_Year_Original[[#This Row],[Year No.]],'27.5-Year'!$A:$A,0),MONTH('Study Data'!$B$6)+1)} -> 0.03636 | D23: =IF($E$11=27.5,$D$11,0) -> 0 | E23: =_27.5_Year_Original[[#This Row],[Original Basis]]*_27.5_Year_Original[[#This Row],[27.5-Year Rate]] -> 0 | F23: =F22+_27.5_Year_Original[[#This Row],[Annual Depreciation]] -> 0 | H23: =H22+1 -> 3 | I23: =I22+1 -> 2026 | J23: {=INDEX('27.5-Year'!$A$1:$M$32,MATCH(_27.5_Year_Post_CS[[#This Row],[Year No.]],'27.5-Year'!$A:$A,0),MONTH('Study Data'!$B$6)+1)} -> 0.03636 | K23: =IF($E$11=27.5,$G$11,0) -> 0 | L23: =_27.5_Year_Post_CS[[#This Row],[Adj Basis]]*_27.5_Year_Post_CS[[#This Row],[27.5-Year Rate]] -> 0 | M23: =M22+_27.5_Year_Post_CS[[#This Row],[Annual Depreciation]] -> 0 | O23: =O22+1 -> 3 | P23: =P22+1 -> 2026 | Q23: 0.192 | R23: =$G$12-$Q$28 -> 0 | S23: =_5_Year_Post_CS[[#This Row],[Basis]]*_5_Year_Post_CS[[#This Row],[5-Year Rate]] -> 0 | T23: =T22+_5_Year_Post_CS[[#This Row],[Annual Depreciation]] -> 0 | V23: =V22+1 -> 3 | W23: =W22+1 -> 2026 | X23: 0.1749 | Y23: =$G$13-$X$30 -> 0 | Z23: =_7_Year_Post_CS[[#This Row],[Basis]]*_7_Year_Post_CS[[#This Row],[7-Year Rate]] -> 0 | AA23: =AA22+_7_Year_Post_CS[[#This Row],[Annual Depreciation]] -> 0 | AC23: =AC22+1 -> 3 | AD23: =AD22+1 -> 2026 | AE23: 0.0855 | AF23: =$G$14-$AE$38 -> 0 | AG23: =_15_Year_Post_CS[[#This Row],[Basis]]*_15_Year_Post_CS[[#This Row],[15-Year Rate]] -> 0 | AH23: =AH22+_15_Year_Post_CS[[#This Row],[Annual Depreciation]] -> 0
A24: =A23+1 -> 4 | B24: =B23+1 -> 2027 | C24: {=INDEX('27.5-Year'!$A$1:$M$32,MATCH(_27.5_Year_Original[[#This Row],[Year No.]],'27.5-Year'!$A:$A,0),MONTH('Study Data'!$B$6)+1)} -> 0.03636 | D24: =IF($E$11=27.5,$D$11,0) -> 0 | E24: =_27.5_Year_Original[[#This Row],[Original Basis]]*_27.5_Year_Original[[#This Row],[27.5-Year Rate]] -> 0 | F24: =F23+_27.5_Year_Original[[#This Row],[Annual Depreciation]] -> 0 | H24: =H23+1 -> 4 | I24: =I23+1 -> 2027 | J24: {=INDEX('27.5-Year'!$A$1:$M$32,MATCH(_27.5_Year_Post_CS[[#This Row],[Year No.]],'27.5-Year'!$A:$A,0),MONTH('Study Data'!$B$6)+1)} -> 0.03636 | K24: =IF($E$11=27.5,$G$11,0) -> 0 | L24: =_27.5_Year_Post_CS[[#This Row],[Adj Basis]]*_27.5_Year_Post_CS[[#This Row],[27.5-Year Rate]] -> 0 | M24: =M23+_27.5_Year_Post_CS[[#This Row],[Annual Depreciation]] -> 0 | O24: =O23+1 -> 4 | P24: =P23+1 -> 2027 | Q24: 0.1152 | R24: =$G$12-$Q$28 -> 0 | S24: =_5_Year_Post_CS[[#This Row],[Basis]]*_5_Year_Post_CS[[#This Row],[5-Year Rate]] -> 0 | T24: =T23+_5_Year_Post_CS[[#This Row],[Annual Depreciation]] -> 0 | V24: =V23+1 -> 4 | W24: =W23+1 -> 2027 | X24: 0.1249 | Y24: =$G$13-$X$30 -> 0 | Z24: =_7_Year_Post_CS[[#This Row],[Basis]]*_7_Year_Post_CS[[#This Row],[7-Year Rate]] -> 0 | AA24: =AA23+_7_Year_Post_CS[[#This Row],[Annual Depreciation]] -> 0 | AC24: =AC23+1 -> 4 | AD24: =AD23+1 -> 2027 | AE24: 0.077 | AF24: =$G$14-$AE$38 -> 0 | AG24: =_15_Year_Post_CS[[#This Row],[Basis]]*_15_Year_Post_CS[[#This Row],[15-Year Rate]] -> 0 | AH24: =AH23+_15_Year_Post_CS[[#This Row],[Annual Depreciation]] -> 0
A25: =A24+1 -> 5 | B25: =B24+1 -> 2028 | C25: {=INDEX('27.5-Year'!$A$1:$M$32,MATCH(_27.5_Year_Original[[#This Row],[Year No.]],'27.5-Year'!$A:$A,0),MONTH('Study Data'!$B$6)+1)} -> 0.03636 | D25: =IF($E$11=27.5,$D$11,0) -> 0 | E25: =_27.5_Year_Original[[#This Row],[Original Basis]]*_27.5_Year_Original[[#This Row],[27.5-Year Rate]] -> 0 | F25: =F24+_27.5_Year_Original[[#This Row],[Annual Depreciation]] -> 0 | H25: =H24+1 -> 5 | I25: =I24+1 -> 2028 | J25: {=INDEX('27.5-Year'!$A$1:$M$32,MATCH(_27.5_Year_Post_CS[[#This Row],[Year No.]],'27.5-Year'!$A:$A,0),MONTH('Study Data'!$B$6)+1)} -> 0.03636 | K25: =IF($E$11=27.5,$G$11,0) -> 0 | L25: =_27.5_Year_Post_CS[[#This Row],[Adj Basis]]*_27.5_Year_Post_CS[[#This Row],[27.5-Year Rate]] -> 0 | M25: =M24+_27.5_Year_Post_CS[[#This Row],[Annual Depreciation]] -> 0 | O25: =O24+1 -> 5 | P25: =P24+1 -> 2028 | Q25: 0.1152 | R25: =$G$12-$Q$28 -> 0 | S25: =_5_Year_Post_CS[[#This Row],[Basis]]*_5_Year_Post_CS[[#This Row],[5-Year Rate]] -> 0 | T25: =T24+_5_Year_Post_CS[[#This Row],[Annual Depreciation]] -> 0 | V25: =V24+1 -> 5 | W25: =W24+1 -> 2028 | X25: 0.0893 | Y25: =$G$13-$X$30 -> 0 | Z25: =_7_Year_Post_CS[[#This Row],[Basis]]*_7_Year_Post_CS[[#This Row],[7-Year Rate]] -> 0 | AA25: =AA24+_7_Year_Post_CS[[#This Row],[Annual Depreciation]] -> 0 | AC25: =AC24+1 -> 5 | AD25: =AD24+1 -> 2028 | AE25: 0.0693 | AF25: =$G$14-$AE$38 -> 0 | AG25: =_15_Year_Post_CS[[#This Row],[Basis]]*_15_Year_Post_CS[[#This Row],[15-Year Rate]] -> 0 | AH25: =AH24+_15_Year_Post_CS[[#This Row],[Annual Depreciation]] -> 0
A26: =A25+1 -> 6 | B26: =B25+1 -> 2029 | C26: {=INDEX('27.5-Year'!$A$1:$M$32,MATCH(_27.5_Year_Original[[#This Row],[Year No.]],'27.5-Year'!$A:$A,0),MONTH('Study Data'!$B$6)+1)} -> 0.03636 | D26: =IF($E$11=27.5,$D$11,0) -> 0 | E26: =_27.5_Year_Original[[#This Row],[Original Basis]]*_27.5_Year_Original[[#This Row],[27.5-Year Rate]] -> 0 | F26: =F25+_27.5_Year_Original[[#This Row],[Annual Depreciation]] -> 0 | H26: =H25+1 -> 6 | I26: =I25+1 -> 2029 | J26: {=INDEX('27.5-Year'!$A$1:$M$32,MATCH(_27.5_Year_Post_CS[[#This Row],[Year No.]],'27.5-Year'!$A:$A,0),MONTH('Study Data'!$B$6)+1)} -> 0.03636 | K26: =IF($E$11=27.5,$G$11,0) -> 0 | L26: =_27.5_Year_Post_CS[[#This Row],[Adj Basis]]*_27.5_Year_Post_CS[[#This Row],[27.5-Year Rate]] -> 0 | M26: =M25+_27.5_Year_Post_CS[[#This Row],[Annual Depreciation]] -> 0 | O26: =O25+1 -> 6 | P26: =P25+1 -> 2029 | Q26: 0.0576 | R26: =$G$12-$Q$28 -> 0 | S26: =_5_Year_Post_CS[[#This Row],[Basis]]*_5_Year_Post_CS[[#This Row],[5-Year Rate]] -> 0 | T26: =T25+_5_Year_Post_CS[[#This Row],[Annual Depreciation]] -> 0 | V26: =V25+1 -> 6 | W26: =W25+1 -> 2029 | X26: 0.0892 | Y26: =$G$13-$X$30 -> 0 | Z26: =_7_Year_Post_CS[[#This Row],[Basis]]*_7_Year_Post_CS[[#This Row],[7-Year Rate]] -> 0 | AA26: =AA25+_7_Year_Post_CS[[#This Row],[Annual Depreciation]] -> 0 | AC26: =AC25+1 -> 6 | AD26: =AD25+1 -> 2029 | AE26: 0.0623 | AF26: =$G$14-$AE$38 -> 0 | AG26: =_15_Year_Post_CS[[#This Row],[Basis]]*_15_Year_Post_CS[[#This Row],[15-Year Rate]] -> 0 | AH26: =AH25+_15_Year_Post_CS[[#This Row],[Annual Depreciation]] -> 0
A27: =A26+1 -> 7 | B27: =B26+1 -> 2030 | C27: {=INDEX('27.5-Year'!$A$1:$M$32,MATCH(_27.5_Year_Original[[#This Row],[Year No.]],'27.5-Year'!$A:$A,0),MONTH('Study Data'!$B$6)+1)} -> 0.03636 | D27: =IF($E$11=27.5,$D$11,0) -> 0 | E27: =_27.5_Year_Original[[#This Row],[Original Basis]]*_27.5_Year_Original[[#This Row],[27.5-Year Rate]] -> 0 | F27: =F26+_27.5_Year_Original[[#This Row],[Annual Depreciation]] -> 0 | H27: =H26+1 -> 7 | I27: =I26+1 -> 2030 | J27: {=INDEX('27.5-Year'!$A$1:$M$32,MATCH(_27.5_Year_Post_CS[[#This Row],[Year No.]],'27.5-Year'!$A:$A,0),MONTH('Study Data'!$B$6)+1)} -> 0.03636 | K27: =IF($E$11=27.5,$G$11,0) -> 0 | L27: =_27.5_Year_Post_CS[[#This Row],[Adj Basis]]*_27.5_Year_Post_CS[[#This Row],[27.5-Year Rate]] -> 0 | M27: =M26+_27.5_Year_Post_CS[[#This Row],[Annual Depreciation]] -> 0 | V27: =V26+1 -> 7 | W27: =W26+1 -> 2030 | X27: 0.0893 | Y27: =$G$13-$X$30 -> 0 | Z27: =_7_Year_Post_CS[[#This Row],[Basis]]*_7_Year_Post_CS[[#This Row],[7-Year Rate]] -> 0 | AA27: =AA26+_7_Year_Post_CS[[#This Row],[Annual Depreciation]] -> 0 | AC27: =AC26+1 -> 7 | AD27: =AD26+1 -> 2030 | AE27: 0.059 | AF27: =$G$14-$AE$38 -> 0 | AG27: =_15_Year_Post_CS[[#This Row],[Basis]]*_15_Year_Post_CS[[#This Row],[15-Year Rate]] -> 0 | AH27: =AH26+_15_Year_Post_CS[[#This Row],[Annual Depreciation]] -> 0
A28: =A27+1 -> 8 | B28: =B27+1 -> 2031 | C28: {=INDEX('27.5-Year'!$A$1:$M$32,MATCH(_27.5_Year_Original[[#This Row],[Year No.]],'27.5-Year'!$A:$A,0),MONTH('Study Data'!$B$6)+1)} -> 0.03636 | D28: =IF($E$11=27.5,$D$11,0) -> 0 | E28: =_27.5_Year_Original[[#This Row],[Original Basis]]*_27.5_Year_Original[[#This Row],[27.5-Year Rate]] -> 0 | F28: =F27+_27.5_Year_Original[[#This Row],[Annual Depreciation]] -> 0 | H28: =H27+1 -> 8 | I28: =I27+1 -> 2031 | J28: {=INDEX('27.5-Year'!$A$1:$M$32,MATCH(_27.5_Year_Post_CS[[#This Row],[Year No.]],'27.5-Year'!$A:$A,0),MONTH('Study Data'!$B$6)+1)} -> 0.03636 | K28: =IF($E$11=27.5,$G$11,0) -> 0 | L28: =_27.5_Year_Post_CS[[#This Row],[Adj Basis]]*_27.5_Year_Post_CS[[#This Row],[27.5-Year Rate]] -> 0 | M28: =M27+_27.5_Year_Post_CS[[#This Row],[Annual Depreciation]] -> 0 | O28: Bonus Depreciation | P28: =INDEX(Definitions!$C$2:$C$12,MATCH('Client Summary'!$G$13,Definitions!$A$2:$A$12,1)) -> 0.6 | Q28: =G12*$P$28 -> 0 | V28: =V27+1 -> 8 | W28: =W27+1 -> 2031 | X28: 0.0446 | Y28: =$G$13-$X$30 -> 0 | Z28: =_7_Year_Post_CS[[#This Row],[Basis]]*_7_Year_Post_CS[[#This Row],[7-Year Rate]] -> 0 | AA28: =AA27+_7_Year_Post_CS[[#This Row],[Annual Depreciation]] -> 0 | AC28: =AC27+1 -> 8 | AD28: =AD27+1 -> 2031 | AE28: 0.059 | AF28: =$G$14-$AE$38 -> 0 | AG28: =_15_Year_Post_CS[[#This Row],[Basis]]*_15_Year_Post_CS[[#This Row],[15-Year Rate]] -> 0 | AH28: =AH27+_15_Year_Post_CS[[#This Row],[Annual Depreciation]] -> 0
A29: =A28+1 -> 9 | B29: =B28+1 -> 2032 | C29: {=INDEX('27.5-Year'!$A$1:$M$32,MATCH(_27.5_Year_Original[[#This Row],[Year No.]],'27.5-Year'!$A:$A,0),MONTH('Study Data'!$B$6)+1)} -> 0.03636 | D29: =IF($E$11=27.5,$D$11,0) -> 0 | E29: =_27.5_Year_Original[[#This Row],[Original Basis]]*_27.5_Year_Original[[#This Row],[27.5-Year Rate]] -> 0 | F29: =F28+_27.5_Year_Original[[#This Row],[Annual Depreciation]] -> 0 | H29: =H28+1 -> 9 | I29: =I28+1 -> 2032 | J29: {=INDEX('27.5-Year'!$A$1:$M$32,MATCH(_27.5_Year_Post_CS[[#This Row],[Year No.]],'27.5-Year'!$A:$A,0),MONTH('Study Data'!$B$6)+1)} -> 0.03636 | K29: =IF($E$11=27.5,$G$11,0) -> 0 | L29: =_27.5_Year_Post_CS[[#This Row],[Adj Basis]]*_27.5_Year_Post_CS[[#This Row],[27.5-Year Rate]] -> 0 | M29: =M28+_27.5_Year_Post_CS[[#This Row],[Annual Depreciation]] -> 0 | AC29: =AC28+1 -> 9 | AD29: =AD28+1 -> 2032 | AE29: 0.0591 | AF29: =$G$14-$AE$38 -> 0 | AG29: =_15_Year_Post_CS[[#This Row],[Basis]]*_15_Year_Post_CS[[#This Row],[15-Year Rate]] -> 0 | AH29: =AH28+_15_Year_Post_CS[[#This Row],[Annual Depreciation]] -> 0
A30: =A29+1 -> 10 | B30: =B29+1 -> 2033 | C30: {=INDEX('27.5-Year'!$A$1:$M$32,MATCH(_27.5_Year_Original[[#This Row],[Year No.]],'27.5-Year'!$A:$A,0),MONTH('Study Data'!$B$6)+1)} -> 0.03637 | D30: =IF($E$11=27.5,$D$11,0) -> 0 | E30: =_27.5_Year_Original[[#This Row],[Original Basis]]*_27.5_Year_Original[[#This Row],[27.5-Year Rate]] -> 0 | F30: =F29+_27.5_Year_Original[[#This Row],[Annual Depreciation]] -> 0 | H30: =H29+1 -> 10 | I30: =I29+1 -> 2033 | J30: {=INDEX('27.5-Year'!$A$1:$M$32,MATCH(_27.5_Year_Post_CS[[#This Row],[Year No.]],'27.5-Year'!$A:$A,0),MONTH('Study Data'!$B$6)+1)} -> 0.03637 | K30: =IF($E$11=27.5,$G$11,0) -> 0 | L30: =_27.5_Year_Post_CS[[#This Row],[Adj Basis]]*_27.5_Year_Post_CS[[#This Row],[27.5-Year Rate]] -> 0 | M30: =M29+_27.5_Year_Post_CS[[#This Row],[Annual Depreciation]] -> 0 | V30: Bonus Depreciation | W30: =INDEX(Definitions!$C$2:$C$12,MATCH('Client Summary'!$G$13,Definitions!$A$2:$A$12,1)) -> 0.6 | X30: =$G$13*$W$30 -> 0 | AC30: =AC29+1 -> 10 | AD30: =AD29+1 -> 2033 | AE30: 0.059 | AF30: =$G$14-$AE$38 -> 0 | AG30: =_15_Year_Post_CS[[#This Row],[Basis]]*_15_Year_Post_CS[[#This Row],[15-Year Rate]] -> 0 | AH30: =AH29+_15_Year_Post_CS[[#This Row],[Annual Depreciation]] -> 0
A31: =A30+1 -> 11 | B31: =B30+1 -> 2034 | C31: {=INDEX('27.5-Year'!$A$1:$M$32,MATCH(_27.5_Year_Original[[#This Row],[Year No.]],'27.5-Year'!$A:$A,0),MONTH('Study Data'!$B$6)+1)} -> 0.03636 | D31: =IF($E$11=27.5,$D$11,0) -> 0 | E31: =_27.5_Year_Original[[#This Row],[Original Basis]]*_27.5_Year_Original[[#This Row],[27.5-Year Rate]] -> 0 | F31: =F30+_27.5_Year_Original[[#This Row],[Annual Depreciation]] -> 0 | H31: =H30+1 -> 11 | I31: =I30+1 -> 2034 | J31: {=INDEX('27.5-Year'!$A$1:$M$32,MATCH(_27.5_Year_Post_CS[[#This Row],[Year No.]],'27.5-Year'!$A:$A,0),MONTH('Study Data'!$B$6)+1)} -> 0.03636 | K31: =IF($E$11=27.5,$G$11,0) -> 0 | L31: =_27.5_Year_Post_CS[[#This Row],[Adj Basis]]*_27.5_Year_Post_CS[[#This Row],[27.5-Year Rate]] -> 0 | M31: =M30+_27.5_Year_Post_CS[[#This Row],[Annual Depreciation]] -> 0 | AC31: =AC30+1 -> 11 | AD31: =AD30+1 -> 2034 | AE31: 0.0591 | AF31: =$G$14-$AE$38 -> 0 | AG31: =_15_Year_Post_CS[[#This Row],[Basis]]*_15_Year_Post_CS[[#This Row],[15-Year Rate]] -> 0 | AH31: =AH30+_15_Year_Post_CS[[#This Row],[Annual Depreciation]] -> 0
A32: =A31+1 -> 12 | B32: =B31+1 -> 2035 | C32: {=INDEX('27.5-Year'!$A$1:$M$32,MATCH(_27.5_Year_Original[[#This Row],[Year No.]],'27.5-Year'!$A:$A,0),MONTH('Study Data'!$B$6)+1)} -> 0.03637 | D32: =IF($E$11=27.5,$D$11,0) -> 0 | E32: =_27.5_Year_Original[[#This Row],[Original Basis]]*_27.5_Year_Original[[#This Row],[27.5-Year Rate]] -> 0 | F32: =F31+_27.5_Year_Original[[#This Row],[Annual Depreciation]] -> 0 | H32: =H31+1 -> 12 | I32: =I31+1 -> 2035 | J32: {=INDEX('27.5-Year'!$A$1:$M$32,MATCH(_27.5_Year_Post_CS[[#This Row],[Year No.]],'27.5-Year'!$A:$A,0),MONTH('Study Data'!$B$6)+1)} -> 0.03637 | K32: =IF($E$11=27.5,$G$11,0) -> 0 | L32: =_27.5_Year_Post_CS[[#This Row],[Adj Basis]]*_27.5_Year_Post_CS[[#This Row],[27.5-Year Rate]] -> 0 | M32: =M31+_27.5_Year_Post_CS[[#This Row],[Annual Depreciation]] -> 0 | AC32: =AC31+1 -> 12 | AD32: =AD31+1 -> 2035 | AE32: 0.059 | AF32: =$G$14-$AE$38 -> 0 | AG32: =_15_Year_Post_CS[[#This Row],[Basis]]*_15_Year_Post_CS[[#This Row],[15-Year Rate]] -> 0 | AH32: =AH31+_15_Year_Post_CS[[#This Row],[Annual Depreciation]] -> 0
A33: =A32+1 -> 13 | B33: =B32+1 -> 2036 | C33: {=INDEX('27.5-Year'!$A$1:$M$32,MATCH(_27.5_Year_Original[[#This Row],[Year No.]],'27.5-Year'!$A:$A,0),MONTH('Study Data'!$B$6)+1)} -> 0.03636 | D33: =IF($E$11=27.5,$D$11,0) -> 0 | E33: =_27.5_Year_Original[[#This Row],[Original Basis]]*_27.5_Year_Original[[#This Row],[27.5-Year Rate]] -> 0 | F33: =F32+_27.5_Year_Original[[#This Row],[Annual Depreciation]] -> 0 | H33: =H32+1 -> 13 | I33: =I32+1 -> 2036 | J33: {=INDEX('27.5-Year'!$A$1:$M$32,MATCH(_27.5_Year_Post_CS[[#This Row],[Year No.]],'27.5-Year'!$A:$A,0),MONTH('Study Data'!$B$6)+1)} -> 0.03636 | K33: =IF($E$11=27.5,$G$11,0) -> 0 | L33: =_27.5_Year_Post_CS[[#This Row],[Adj Basis]]*_27.5_Year_Post_CS[[#This Row],[27.5-Year Rate]] -> 0 | M33: =M32+_27.5_Year_Post_CS[[#This Row],[Annual Depreciation]] -> 0 | AC33: =AC32+1 -> 13 | AD33: =AD32+1 -> 2036 | AE33: 0.0591 | AF33: =$G$14-$AE$38 -> 0 | AG33: =_15_Year_Post_CS[[#This Row],[Basis]]*_15_Year_Post_CS[[#This Row],[15-Year Rate]] -> 0 | AH33: =AH32+_15_Year_Post_CS[[#This Row],[Annual Depreciation]] -> 0
A34: =A33+1 -> 14 | B34: =B33+1 -> 2037 | C34: {=INDEX('27.5-Year'!$A$1:$M$32,MATCH(_27.5_Year_Original[[#This Row],[Year No.]],'27.5-Year'!$A:$A,0),MONTH('Study Data'!$B$6)+1)} -> 0.03637 | D34: =IF($E$11=27.5,$D$11,0) -> 0 | E34: =_27.5_Year_Original[[#This Row],[Original Basis]]*_27.5_Year_Original[[#This Row],[27.5-Year Rate]] -> 0 | F34: =F33+_27.5_Year_Original[[#This Row],[Annual Depreciation]] -> 0 | H34: =H33+1 -> 14 | I34: =I33+1 -> 2037 | J34: {=INDEX('27.5-Year'!$A$1:$M$32,MATCH(_27.5_Year_Post_CS[[#This Row],[Year No.]],'27.5-Year'!$A:$A,0),MONTH('Study Data'!$B$6)+1)} -> 0.03637 | K34: =IF($E$11=27.5,$G$11,0) -> 0 | L34: =_27.5_Year_Post_CS[[#This Row],[Adj Basis]]*_27.5_Year_Post_CS[[#This Row],[27.5-Year Rate]] -> 0 | M34: =M33+_27.5_Year_Post_CS[[#This Row],[Annual Depreciation]] -> 0 | AC34: =AC33+1 -> 14 | AD34: =AD33+1 -> 2037 | AE34: 0.059 | AF34: =$G$14-$AE$38 -> 0 | AG34: =_15_Year_Post_CS[[#This Row],[Basis]]*_15_Year_Post_CS[[#This Row],[15-Year Rate]] -> 0 | AH34: =AH33+_15_Year_Post_CS[[#This Row],[Annual Depreciation]] -> 0
A35: =A34+1 -> 15 | B35: =B34+1 -> 2038 | C35: {=INDEX('27.5-Year'!$A$1:$M$32,MATCH(_27.5_Year_Original[[#This Row],[Year No.]],'27.5-Year'!$A:$A,0),MONTH('Study Data'!$B$6)+1)} -> 0.03636 | D35: =IF($E$11=27.5,$D$11,0) -> 0 | E35: =_27.5_Year_Original[[#This Row],[Original Basis]]*_27.5_Year_Original[[#This Row],[27.5-Year Rate]] -> 0 | F35: =F34+_27.5_Year_Original[[#This Row],[Annual Depreciation]] -> 0 | H35: =H34+1 -> 15 | I35: =I34+1 -> 2038 | J35: {=INDEX('27.5-Year'!$A$1:$M$32,MATCH(_27.5_Year_Post_CS[[#This Row],[Year No.]],'27.5-Year'!$A:$A,0),MONTH('Study Data'!$B$6)+1)} -> 0.03636 | K35: =IF($E$11=27.5,$G$11,0) -> 0 | L35: =_27.5_Year_Post_CS[[#This Row],[Adj Basis]]*_27.5_Year_Post_CS[[#This Row],[27.5-Year Rate]] -> 0 | M35: =M34+_27.5_Year_Post_CS[[#This Row],[Annual Depreciation]] -> 0 | AC35: =AC34+1 -> 15 | AD35: =AD34+1 -> 2038 | AE35: 0.0591 | AF35: =$G$14-$AE$38 -> 0 | AG35: =_15_Year_Post_CS[[#This Row],[Basis]]*_15_Year_Post_CS[[#This Row],[15-Year Rate]] -> 0 | AH35: =AH34+_15_Year_Post_CS[[#This Row],[Annual Depreciation]] -> 0
A36: =A35+1 -> 16 | B36: =B35+1 -> 2039 | C36: {=INDEX('27.5-Year'!$A$1:$M$32,MATCH(_27.5_Year_Original[[#This Row],[Year No.]],'27.5-Year'!$A:$A,0),MONTH('Study Data'!$B$6)+1)} -> 0.03637 | D36: =IF($E$11=27.5,$D$11,0) -> 0 | E36: =_27.5_Year_Original[[#This Row],[Original Basis]]*_27.5_Year_Original[[#This Row],[27.5-Year Rate]] -> 0 | F36: =F35+_27.5_Year_Original[[#This Row],[Annual Depreciation]] -> 0 | H36: =H35+1 -> 16 | I36: =I35+1 -> 2039 | J36: {=INDEX('27.5-Year'!$A$1:$M$32,MATCH(_27.5_Year_Post_CS[[#This Row],[Year No.]],'27.5-Year'!$A:$A,0),MONTH('Study Data'!$B$6)+1)} -> 0.03637 | K36: =IF($E$11=27.5,$G$11,0) -> 0 | L36: =_27.5_Year_Post_CS[[#This Row],[Adj Basis]]*_27.5_Year_Post_CS[[#This Row],[27.5-Year Rate]] -> 0 | M36: =M35+_27.5_Year_Post_CS[[#This Row],[Annual Depreciation]] -> 0 | AC36: =AC35+1 -> 16 | AD36: =AD35+1 -> 2039 | AE36: 0.0295 | AF36: =$G$14-$AE$38 -> 0 | AG36: =_15_Year_Post_CS[[#This Row],[Basis]]*_15_Year_Post_CS[[#This Row],[15-Year Rate]] -> 0 | AH36: =AH35+_15_Year_Post_CS[[#This Row],[Annual Depreciation]] -> 0
A37: =A36+1 -> 17 | B37: =B36+1 -> 2040 | C37: {=INDEX('27.5-Year'!$A$1:$M$32,MATCH(_27.5_Year_Original[[#This Row],[Year No.]],'27.5-Year'!$A:$A,0),MONTH('Study Data'!$B$6)+1)} -> 0.03636 | D37: =IF($E$11=27.5,$D$11,0) -> 0 | E37: =_27.5_Year_Original[[#This Row],[Original Basis]]*_27.5_Year_Original[[#This Row],[27.5-Year Rate]] -> 0 | F37: =F36+_27.5_Year_Original[[#This Row],[Annual Depreciation]] -> 0 | H37: =H36+1 -> 17 | I37: =I36+1 -> 2040 | J37: {=INDEX('27.5-Year'!$A$1:$M$32,MATCH(_27.5_Year_Post_CS[[#This Row],[Year No.]],'27.5-Year'!$A:$A,0),MONTH('Study Data'!$B$6)+1)} -> 0.03636 | K37: =IF($E$11=27.5,$G$11,0) -> 0 | L37: =_27.5_Year_Post_CS[[#This Row],[Adj Basis]]*_27.5_Year_Post_CS[[#This Row],[27.5-Year Rate]] -> 0 | M37: =M36+_27.5_Year_Post_CS[[#This Row],[Annual Depreciation]] -> 0
A38: =A37+1 -> 18 | B38: =B37+1 -> 2041 | C38: {=INDEX('27.5-Year'!$A$1:$M$32,MATCH(_27.5_Year_Original[[#This Row],[Year No.]],'27.5-Year'!$A:$A,0),MONTH('Study Data'!$B$6)+1)} -> 0.03637 | D38: =IF($E$11=27.5,$D$11,0) -> 0 | E38: =_27.5_Year_Original[[#This Row],[Original Basis]]*_27.5_Year_Original[[#This Row],[27.5-Year Rate]] -> 0 | F38: =F37+_27.5_Year_Original[[#This Row],[Annual Depreciation]] -> 0 | H38: =H37+1 -> 18 | I38: =I37+1 -> 2041 | J38: {=INDEX('27.5-Year'!$A$1:$M$32,MATCH(_27.5_Year_Post_CS[[#This Row],[Year No.]],'27.5-Year'!$A:$A,0),MONTH('Study Data'!$B$6)+1)} -> 0.03637 | K38: =IF($E$11=27.5,$G$11,0) -> 0 | L38: =_27.5_Year_Post_CS[[#This Row],[Adj Basis]]*_27.5_Year_Post_CS[[#This Row],[27.5-Year Rate]] -> 0 | M38: =M37+_27.5_Year_Post_CS[[#This Row],[Annual Depreciation]] -> 0 | AC38: Bonus Depreciation | AD38: =INDEX(Definitions!$C$2:$C$12,MATCH('Client Summary'!$G$13,Definitions!$A$2:$A$12,1)) -> 0.6 | AE38: =$G$14*$AD$38 -> 0
A39: =A38+1 -> 19 | B39: =B38+1 -> 2042 | C39: {=INDEX('27.5-Year'!$A$1:$M$32,MATCH(_27.5_Year_Original[[#This Row],[Year No.]],'27.5-Year'!$A:$A,0),MONTH('Study Data'!$B$6)+1)} -> 0.03636 | D39: =IF($E$11=27.5,$D$11,0) -> 0 | E39: =_27.5_Year_Original[[#This Row],[Original Basis]]*_27.5_Year_Original[[#This Row],[27.5-Year Rate]] -> 0 | F39: =F38+_27.5_Year_Original[[#This Row],[Annual Depreciation]] -> 0 | H39: =H38+1 -> 19 | I39: =I38+1 -> 2042 | J39: {=INDEX('27.5-Year'!$A$1:$M$32,MATCH(_27.5_Year_Post_CS[[#This Row],[Year No.]],'27.5-Year'!$A:$A,0),MONTH('Study Data'!$B$6)+1)} -> 0.03636 | K39: =IF($E$11=27.5,$G$11,0) -> 0 | L39: =_27.5_Year_Post_CS[[#This Row],[Adj Basis]]*_27.5_Year_Post_CS[[#This Row],[27.5-Year Rate]] -> 0 | M39: =M38+_27.5_Year_Post_CS[[#This Row],[Annual Depreciation]] -> 0
A40: =A39+1 -> 20 | B40: =B39+1 -> 2043 | C40: {=INDEX('27.5-Year'!$A$1:$M$32,MATCH(_27.5_Year_Original[[#This Row],[Year No.]],'27.5-Year'!$A:$A,0),MONTH('Study Data'!$B$6)+1)} -> 0.03637 | D40: =IF($E$11=27.5,$D$11,0) -> 0 | E40: =_27.5_Year_Original[[#This Row],[Original Basis]]*_27.5_Year_Original[[#This Row],[27.5-Year Rate]] -> 0 | F40: =F39+_27.5_Year_Original[[#This Row],[Annual Depreciation]] -> 0 | H40: =H39+1 -> 20 | I40: =I39+1 -> 2043 | J40: {=INDEX('27.5-Year'!$A$1:$M$32,MATCH(_27.5_Year_Post_CS[[#This Row],[Year No.]],'27.5-Year'!$A:$A,0),MONTH('Study Data'!$B$6)+1)} -> 0.03637 | K40: =IF($E$11=27.5,$G$11,0) -> 0 | L40: =_27.5_Year_Post_CS[[#This Row],[Adj Basis]]*_27.5_Year_Post_CS[[#This Row],[27.5-Year Rate]] -> 0 | M40: =M39+_27.5_Year_Post_CS[[#This Row],[Annual Depreciation]] -> 0
A41: =A40+1 -> 21 | B41: =B40+1 -> 2044 | C41: {=INDEX('27.5-Year'!$A$1:$M$32,MATCH(_27.5_Year_Original[[#This Row],[Year No.]],'27.5-Year'!$A:$A,0),MONTH('Study Data'!$B$6)+1)} -> 0.03636 | D41: =IF($E$11=27.5,$D$11,0) -> 0 | E41: =_27.5_Year_Original[[#This Row],[Original Basis]]*_27.5_Year_Original[[#This Row],[27.5-Year Rate]] -> 0 | F41: =F40+_27.5_Year_Original[[#This Row],[Annual Depreciation]] -> 0 | H41: =H40+1 -> 21 | I41: =I40+1 -> 2044 | J41: {=INDEX('27.5-Year'!$A$1:$M$32,MATCH(_27.5_Year_Post_CS[[#This Row],[Year No.]],'27.5-Year'!$A:$A,0),MONTH('Study Data'!$B$6)+1)} -> 0.03636 | K41: =IF($E$11=27.5,$G$11,0) -> 0 | L41: =_27.5_Year_Post_CS[[#This Row],[Adj Basis]]*_27.5_Year_Post_CS[[#This Row],[27.5-Year Rate]] -> 0 | M41: =M40+_27.5_Year_Post_CS[[#This Row],[Annual Depreciation]] -> 0
A42: =A41+1 -> 22 | B42: =B41+1 -> 2045 | C42: {=INDEX('27.5-Year'!$A$1:$M$32,MATCH(_27.5_Year_Original[[#This Row],[Year No.]],'27.5-Year'!$A:$A,0),MONTH('Study Data'!$B$6)+1)} -> 0.03637 | D42: =IF($E$11=27.5,$D$11,0) -> 0 | E42: =_27.5_Year_Original[[#This Row],[Original Basis]]*_27.5_Year_Original[[#This Row],[27.5-Year Rate]] -> 0 | F42: =F41+_27.5_Year_Original[[#This Row],[Annual Depreciation]] -> 0 | H42: =H41+1 -> 22 | I42: =I41+1 -> 2045 | J42: {=INDEX('27.5-Year'!$A$1:$M$32,MATCH(_27.5_Year_Post_CS[[#This Row],[Year No.]],'27.5-Year'!$A:$A,0),MONTH('Study Data'!$B$6)+1)} -> 0.03637 | K42: =IF($E$11=27.5,$G$11,0) -> 0 | L42: =_27.5_Year_Post_CS[[#This Row],[Adj Basis]]*_27.5_Year_Post_CS[[#This Row],[27.5-Year Rate]] -> 0 | M42: =M41+_27.5_Year_Post_CS[[#This Row],[Annual Depreciation]] -> 0
A43: =A42+1 -> 23 | B43: =B42+1 -> 2046 | C43: {=INDEX('27.5-Year'!$A$1:$M$32,MATCH(_27.5_Year_Original[[#This Row],[Year No.]],'27.5-Year'!$A:$A,0),MONTH('Study Data'!$B$6)+1)} -> 0.03636 | D43: =IF($E$11=27.5,$D$11,0) -> 0 | E43: =_27.5_Year_Original[[#This Row],[Original Basis]]*_27.5_Year_Original[[#This Row],[27.5-Year Rate]] -> 0 | F43: =F42+_27.5_Year_Original[[#This Row],[Annual Depreciation]] -> 0 | H43: =H42+1 -> 23 | I43: =I42+1 -> 2046 | J43: {=INDEX('27.5-Year'!$A$1:$M$32,MATCH(_27.5_Year_Post_CS[[#This Row],[Year No.]],'27.5-Year'!$A:$A,0),MONTH('Study Data'!$B$6)+1)} -> 0.03636 | K43: =IF($E$11=27.5,$G$11,0) -> 0 | L43: =_27.5_Year_Post_CS[[#This Row],[Adj Basis]]*_27.5_Year_Post_CS[[#This Row],[27.5-Year Rate]] -> 0 | M43: =M42+_27.5_Year_Post_CS[[#This Row],[Annual Depreciation]] -> 0
A44: =A43+1 -> 24 | B44: =B43+1 -> 2047 | C44: {=INDEX('27.5-Year'!$A$1:$M$32,MATCH(_27.5_Year_Original[[#This Row],[Year No.]],'27.5-Year'!$A:$A,0),MONTH('Study Data'!$B$6)+1)} -> 0.03637 | D44: =IF($E$11=27.5,$D$11,0) -> 0 | E44: =_27.5_Year_Original[[#This Row],[Original Basis]]*_27.5_Year_Original[[#This Row],[27.5-Year Rate]] -> 0 | F44: =F43+_27.5_Year_Original[[#This Row],[Annual Depreciation]] -> 0 | H44: =H43+1 -> 24 | I44: =I43+1 -> 2047 | J44: {=INDEX('27.5-Year'!$A$1:$M$32,MATCH(_27.5_Year_Post_CS[[#This Row],[Year No.]],'27.5-Year'!$A:$A,0),MONTH('Study Data'!$B$6)+1)} -> 0.03637 | K44: =IF($E$11=27.5,$G$11,0) -> 0 | L44: =_27.5_Year_Post_CS[[#This Row],[Adj Basis]]*_27.5_Year_Post_CS[[#This Row],[27.5-Year Rate]] -> 0 | M44: =M43+_27.5_Year_Post_CS[[#This Row],[Annual Depreciation]] -> 0
A45: =A44+1 -> 25 | B45: =B44+1 -> 2048 | C45: {=INDEX('27.5-Year'!$A$1:$M$32,MATCH(_27.5_Year_Original[[#This Row],[Year No.]],'27.5-Year'!$A:$A,0),MONTH('Study Data'!$B$6)+1)} -> 0.03636 | D45: =IF($E$11=27.5,$D$11,0) -> 0 | E45: =_27.5_Year_Original[[#This Row],[Original Basis]]*_27.5_Year_Original[[#This Row],[27.5-Year Rate]] -> 0 | F45: =F44+_27.5_Year_Original[[#This Row],[Annual Depreciation]] -> 0 | H45: =H44+1 -> 25 | I45: =I44+1 -> 2048 | J45: {=INDEX('27.5-Year'!$A$1:$M$32,MATCH(_27.5_Year_Post_CS[[#This Row],[Year No.]],'27.5-Year'!$A:$A,0),MONTH('Study Data'!$B$6)+1)} -> 0.03636 | K45: =IF($E$11=27.5,$G$11,0) -> 0 | L45: =_27.5_Year_Post_CS[[#This Row],[Adj Basis]]*_27.5_Year_Post_CS[[#This Row],[27.5-Year Rate]] -> 0 | M45: =M44+_27.5_Year_Post_CS[[#This Row],[Annual Depreciation]] -> 0
A46: =A45+1 -> 26 | B46: =B45+1 -> 2049 | C46: {=INDEX('27.5-Year'!$A$1:$M$32,MATCH(_27.5_Year_Original[[#This Row],[Year No.]],'27.5-Year'!$A:$A,0),MONTH('Study Data'!$B$6)+1)} -> 0.03637 | D46: =IF($E$11=27.5,$D$11,0) -> 0 | E46: =_27.5_Year_Original[[#This Row],[Original Basis]]*_27.5_Year_Original[[#This Row],[27.5-Year Rate]] -> 0 | F46: =F45+_27.5_Year_Original[[#This Row],[Annual Depreciation]] -> 0 | H46: =H45+1 -> 26 | I46: =I45+1 -> 2049 | J46: {=INDEX('27.5-Year'!$A$1:$M$32,MATCH(_27.5_Year_Post_CS[[#This Row],[Year No.]],'27.5-Year'!$A:$A,0),MONTH('Study Data'!$B$6)+1)} -> 0.03637 | K46: =IF($E$11=27.5,$G$11,0) -> 0 | L46: =_27.5_Year_Post_CS[[#This Row],[Adj Basis]]*_27.5_Year_Post_CS[[#This Row],[27.5-Year Rate]] -> 0 | M46: =M45+_27.5_Year_Post_CS[[#This Row],[Annual Depreciation]] -> 0
A47: =A46+1 -> 27 | B47: =B46+1 -> 2050 | C47: {=INDEX('27.5-Year'!$A$1:$M$32,MATCH(_27.5_Year_Original[[#This Row],[Year No.]],'27.5-Year'!$A:$A,0),MONTH('Study Data'!$B$6)+1)} -> 0.03636 | D47: =IF($E$11=27.5,$D$11,0) -> 0 | E47: =_27.5_Year_Original[[#This Row],[Original Basis]]*_27.5_Year_Original[[#This Row],[27.5-Year Rate]] -> 0 | F47: =F46+_27.5_Year_Original[[#This Row],[Annual Depreciation]] -> 0 | H47: =H46+1 -> 27 | I47: =I46+1 -> 2050 | J47: {=INDEX('27.5-Year'!$A$1:$M$32,MATCH(_27.5_Year_Post_CS[[#This Row],[Year No.]],'27.5-Year'!$A:$A,0),MONTH('Study Data'!$B$6)+1)} -> 0.03636 | K47: =IF($E$11=27.5,$G$11,0) -> 0 | L47: =_27.5_Year_Post_CS[[#This Row],[Adj Basis]]*_27.5_Year_Post_CS[[#This Row],[27.5-Year Rate]] -> 0 | M47: =M46+_27.5_Year_Post_CS[[#This Row],[Annual Depreciation]] -> 0
A48: =A47+1 -> 28 | B48: =B47+1 -> 2051 | C48: {=INDEX('27.5-Year'!$A$1:$M$32,MATCH(_27.5_Year_Original[[#This Row],[Year No.]],'27.5-Year'!$A:$A,0),MONTH('Study Data'!$B$6)+1)} -> 0.0197 | D48: =IF($E$11=27.5,$D$11,0) -> 0 | E48: =_27.5_Year_Original[[#This Row],[Original Basis]]*_27.5_Year_Original[[#This Row],[27.5-Year Rate]] -> 0 | F48: =F47+_27.5_Year_Original[[#This Row],[Annual Depreciation]] -> 0 | H48: =H47+1 -> 28 | I48: =I47+1 -> 2051 | J48: {=INDEX('27.5-Year'!$A$1:$M$32,MATCH(_27.5_Year_Post_CS[[#This Row],[Year No.]],'27.5-Year'!$A:$A,0),MONTH('Study Data'!$B$6)+1)} -> 0.0197 | K48: =IF($E$11=27.5,$G$11,0) -> 0 | L48: =_27.5_Year_Post_CS[[#This Row],[Adj Basis]]*_27.5_Year_Post_CS[[#This Row],[27.5-Year Rate]] -> 0 | M48: =M47+_27.5_Year_Post_CS[[#This Row],[Annual Depreciation]] -> 0
A49: =A48+1 -> 29 | B49: =B48+1 -> 2052 | C49: {=INDEX('27.5-Year'!$A$1:$M$32,MATCH(_27.5_Year_Original[[#This Row],[Year No.]],'27.5-Year'!$A:$A,0),MONTH('Study Data'!$B$6)+1)} -> 0 | D49: =IF($E$11=27.5,$D$11,0) -> 0 | E49: =_27.5_Year_Original[[#This Row],[Original Basis]]*_27.5_Year_Original[[#This Row],[27.5-Year Rate]] -> 0 | F49: =F48+_27.5_Year_Original[[#This Row],[Annual Depreciation]] -> 0 | H49: =H48+1 -> 29 | I49: =I48+1 -> 2052 | J49: {=INDEX('27.5-Year'!$A$1:$M$32,MATCH(_27.5_Year_Post_CS[[#This Row],[Year No.]],'27.5-Year'!$A:$A,0),MONTH('Study Data'!$B$6)+1)} -> 0 | K49: =IF($E$11=27.5,$G$11,0) -> 0 | L49: =_27.5_Year_Post_CS[[#This Row],[Adj Basis]]*_27.5_Year_Post_CS[[#This Row],[27.5-Year Rate]] -> 0 | M49: =M48+_27.5_Year_Post_CS[[#This Row],[Annual Depreciation]] -> 0
A52: Building (Pre CS Study) | H52: Building (Post CS Study)
A53: 39 Yr SL | H53: 39 Yr SL
A54: Year No. | B54: Year | C54: 39-Year Rate | D54: Original Basis | E54: Annual Depreciation | F54: Cumulative Depreciation | H54: Year No. | I54: Year | J54: 39-Year Rate | K54: Adj Basis | L54: Annual Depreciation | M54: Cumulative Depreciation
A55: 1 | B55: =IF($B$6>0,YEAR($B$6),"") -> 2024 | C55: {=INDEX('39-Year'!$A$1:$M$43,MATCH(_27.5_Year_Original11[[#This Row],[Year No.]],'39-Year'!$A:$A,0),MONTH($B$6)+1)} -> 0.02461 | D55: =IF($E$11=39,$D$11,0) -> 0 | E55: =_27.5_Year_Original11[[#This Row],[Original Basis]]*_27.5_Year_Original11[[#This Row],[39-Year Rate]] -> 0 | F55: =E55 -> 0 | H55: 1 | I55: =IF($B$6>0,YEAR($B$6),"") -> 2024 | J55: {=INDEX('39-Year'!$A$1:$M$43,MATCH(_39_Year_Post_CS12[[#This Row],[Year No.]],'39-Year'!$A:$A,0),MONTH($B$6)+1)} -> 0.02461 | K55: =IF($E$11=39,$G$11,0) -> 0 | L55: =_39_Year_Post_CS12[[#This Row],[Adj Basis]]*_39_Year_Post_CS12[[#This Row],[39-Year Rate]] -> 0 | M55: =L55 -> 0
A56: =A55+1 -> 2 | B56: =B55+1 -> 2025 | C56: {=INDEX('39-Year'!$A$1:$M$43,MATCH(_27.5_Year_Original11[[#This Row],[Year No.]],'39-Year'!$A:$A,0),MONTH($B$6)+1)} -> 0.02564 | D56: =IF($E$11=39,$D$11,0) -> 0 | E56: =_27.5_Year_Original11[[#This Row],[Original Basis]]*_27.5_Year_Original11[[#This Row],[39-Year Rate]] -> 0 | F56: =F55+_27.5_Year_Original11[[#This Row],[Annual Depreciation]] -> 0 | H56: =H55+1 -> 2 | I56: =I55+1 -> 2025 | J56: {=INDEX('39-Year'!$A$1:$M$43,MATCH(_39_Year_Post_CS12[[#This Row],[Year No.]],'39-Year'!$A:$A,0),MONTH($B$6)+1)} -> 0.02564 | K56: =IF($E$11=39,$G$11,0) -> 0 | L56: =_39_Year_Post_CS12[[#This Row],[Adj Basis]]*_39_Year_Post_CS12[[#This Row],[39-Year Rate]] -> 0 | M56: =M55+_39_Year_Post_CS12[[#This Row],[Annual Depreciation]] -> 0
A57: =A56+1 -> 3 | B57: =B56+1 -> 2026 | C57: {=INDEX('39-Year'!$A$1:$M$43,MATCH(_27.5_Year_Original11[[#This Row],[Year No.]],'39-Year'!$A:$A,0),MONTH($B$6)+1)} -> 0.02564 | D57: =IF($E$11=39,$D$11,0) -> 0 | E57: =_27.5_Year_Original11[[#This Row],[Original Basis]]*_27.5_Year_Original11[[#This Row],[39-Year Rate]] -> 0 | F57: =F56+_27.5_Year_Original11[[#This Row],[Annual Depreciation]] -> 0 | H57: =H56+1 -> 3 | I57: =I56+1 -> 2026 | J57: {=INDEX('39-Year'!$A$1:$M$43,MATCH(_39_Year_Post_CS12[[#This Row],[Year No.]],'39-Year'!$A:$A,0),MONTH($B$6)+1)} -> 0.02564 | K57: =IF($E$11=39,$G$11,0) -> 0 | L57: =_39_Year_Post_CS12[[#This Row],[Adj Basis]]*_39_Year_Post_CS12[[#This Row],[39-Year Rate]] -> 0 | M57: =M56+_39_Year_Post_CS12[[#This Row],[Annual Depreciation]] -> 0
A58: =A57+1 -> 4 | B58: =B57+1 -> 2027 | C58: {=INDEX('39-Year'!$A$1:$M$43,MATCH(_27.5_Year_Original11[[#This Row],[Year No.]],'39-Year'!$A:$A,0),MONTH($B$6)+1)} -> 0.02564 | D58: =IF($E$11=39,$D$11,0) -> 0 | E58: =_27.5_Year_Original11[[#This Row],[Original Basis]]*_27.5_Year_Original11[[#This Row],[39-Year Rate]] -> 0 | F58: =F57+_27.5_Year_Original11[[#This Row],[Annual Depreciation]] -> 0 | H58: =H57+1 -> 4 | I58: =I57+1 -> 2027 | J58: {=INDEX('39-Year'!$A$1:$M$43,MATCH(_39_Year_Post_CS12[[#This Row],[Year No.]],'39-Year'!$A:$A,0),MONTH($B$6)+1)} -> 0.02564 | K58: =IF($E$11=39,$G$11,0) -> 0 | L58: =_39_Year_Post_CS12[[#This Row],[Adj Basis]]*_39_Year_Post_CS12[[#This Row],[39-Year Rate]] -> 0 | M58: =M57+_39_Year_Post_CS12[[#This Row],[Annual Depreciation]] -> 0
A59: =A58+1 -> 5 | B59: =B58+1 -> 2028 | C59: {=INDEX('39-Year'!$A$1:$M$43,MATCH(_27.5_Year_Original11[[#This Row],[Year No.]],'39-Year'!$A:$A,0),MONTH($B$6)+1)} -> 0.02564 | D59: =IF($E$11=39,$D$11,0) -> 0 | E59: =_27.5_Year_Original11[[#This Row],[Original Basis]]*_27.5_Year_Original11[[#This Row],[39-Year Rate]] -> 0 | F59: =F58+_27.5_Year_Original11[[#This Row],[Annual Depreciation]] -> 0 | H59: =H58+1 -> 5 | I59: =I58+1 -> 2028 | J59: {=INDEX('39-Year'!$A$1:$M$43,MATCH(_39_Year_Post_CS12[[#This Row],[Year No.]],'39-Year'!$A:$A,0),MONTH($B$6)+1)} -> 0.02564 | K59: =IF($E$11=39,$G$11,0) -> 0 | L59: =_39_Year_Post_CS12[[#This Row],[Adj Basis]]*_39_Year_Post_CS12[[#This Row],[39-Year Rate]] -> 0 | M59: =M58+_39_Year_Post_CS12[[#This Row],[Annual Depreciation]] -> 0
A60: =A59+1 -> 6 | B60: =B59+1 -> 2029 | C60: {=INDEX('39-Year'!$A$1:$M$43,MATCH(_27.5_Year_Original11[[#This Row],[Year No.]],'39-Year'!$A:$A,0),MONTH($B$6)+1)} -> 0.02564 | D60: =IF($E$11=39,$D$11,0) -> 0 | E60: =_27.5_Year_Original11[[#This Row],[Original Basis]]*_27.5_Year_Original11[[#This Row],[39-Year Rate]] -> 0 | F60: =F59+_27.5_Year_Original11[[#This Row],[Annual Depreciation]] -> 0 | H60: =H59+1 -> 6 | I60: =I59+1 -> 2029 | J60: {=INDEX('39-Year'!$A$1:$M$43,MATCH(_39_Year_Post_CS12[[#This Row],[Year No.]],'39-Year'!$A:$A,0),MONTH($B$6)+1)} -> 0.02564 | K60: =IF($E$11=39,$G$11,0) -> 0 | L60: =_39_Year_Post_CS12[[#This Row],[Adj Basis]]*_39_Year_Post_CS12[[#This Row],[39-Year Rate]] -> 0 | M60: =M59+_39_Year_Post_CS12[[#This Row],[Annual Depreciation]] -> 0
A61: =A60+1 -> 7 | B61: =B60+1 -> 2030 | C61: {=INDEX('39-Year'!$A$1:$M$43,MATCH(_27.5_Year_Original11[[#This Row],[Year No.]],'39-Year'!$A:$A,0),MONTH($B$6)+1)} -> 0.02564 | D61: =IF($E$11=39,$D$11,0) -> 0 | E61: =_27.5_Year_Original11[[#This Row],[Original Basis]]*_27.5_Year_Original11[[#This Row],[39-Year Rate]] -> 0 | F61: =F60+_27.5_Year_Original11[[#This Row],[Annual Depreciation]] -> 0 | H61: =H60+1 -> 7 | I61: =I60+1 -> 2030 | J61: {=INDEX('39-Year'!$A$1:$M$43,MATCH(_39_Year_Post_CS12[[#This Row],[Year No.]],'39-Year'!$A:$A,0),MONTH($B$6)+1)} -> 0.02564 | K61: =IF($E$11=39,$G$11,0) -> 0 | L61: =_39_Year_Post_CS12[[#This Row],[Adj Basis]]*_39_Year_Post_CS12[[#This Row],[39-Year Rate]] -> 0 | M61: =M60+_39_Year_Post_CS12[[#This Row],[Annual Depreciation]] -> 0
A62: =A61+1 -> 8 | B62: =B61+1 -> 2031 | C62: {=INDEX('39-Year'!$A$1:$M$43,MATCH(_27.5_Year_Original11[[#This Row],[Year No.]],'39-Year'!$A:$A,0),MONTH($B$6)+1)} -> 0.02564 | D62: =IF($E$11=39,$D$11,0) -> 0 | E62: =_27.5_Year_Original11[[#This Row],[Original Basis]]*_27.5_Year_Original11[[#This Row],[39-Year Rate]] -> 0 | F62: =F61+_27.5_Year_Original11[[#This Row],[Annual Depreciation]] -> 0 | H62: =H61+1 -> 8 | I62: =I61+1 -> 2031 | J62: {=INDEX('39-Year'!$A$1:$M$43,MATCH(_39_Year_Post_CS12[[#This Row],[Year No.]],'39-Year'!$A:$A,0),MONTH($B$6)+1)} -> 0.02564 | K62: =IF($E$11=39,$G$11,0) -> 0 | L62: =_39_Year_Post_CS12[[#This Row],[Adj Basis]]*_39_Year_Post_CS12[[#This Row],[39-Year Rate]] -> 0 | M62: =M61+_39_Year_Post_CS12[[#This Row],[Annual Depreciation]] -> 0
A63: =A62+1 -> 9 | B63: =B62+1 -> 2032 | C63: {=INDEX('39-Year'!$A$1:$M$43,MATCH(_27.5_Year_Original11[[#This Row],[Year No.]],'39-Year'!$A:$A,0),MONTH($B$6)+1)} -> 0.02564 | D63: =IF($E$11=39,$D$11,0) -> 0 | E63: =_27.5_Year_Original11[[#This Row],[Original Basis]]*_27.5_Year_Original11[[#This Row],[39-Year Rate]] -> 0 | F63: =F62+_27.5_Year_Original11[[#This Row],[Annual Depreciation]] -> 0 | H63: =H62+1 -> 9 | I63: =I62+1 -> 2032 | J63: {=INDEX('39-Year'!$A$1:$M$43,MATCH(_39_Year_Post_CS12[[#This Row],[Year No.]],'39-Year'!$A:$A,0),MONTH($B$6)+1)} -> 0.02564 | K63: =IF($E$11=39,$G$11,0) -> 0 | L63: =_39_Year_Post_CS12[[#This Row],[Adj Basis]]*_39_Year_Post_CS12[[#This Row],[39-Year Rate]] -> 0 | M63: =M62+_39_Year_Post_CS12[[#This Row],[Annual Depreciation]] -> 0
A64: =A63+1 -> 10 | B64: =B63+1 -> 2033 | C64: {=INDEX('39-Year'!$A$1:$M$43,MATCH(_27.5_Year_Original11[[#This Row],[Year No.]],'39-Year'!$A:$A,0),MONTH($B$6)+1)} -> 0.02564 | D64: =IF($E$11=39,$D$11,0) -> 0 | E64: =_27.5_Year_Original11[[#This Row],[Original Basis]]*_27.5_Year_Original11[[#This Row],[39-Year Rate]] -> 0 | F64: =F63+_27.5_Year_Original11[[#This Row],[Annual Depreciation]] -> 0 | H64: =H63+1 -> 10 | I64: =I63+1 -> 2033 | J64: {=INDEX('39-Year'!$A$1:$M$43,MATCH(_39_Year_Post_CS12[[#This Row],[Year No.]],'39-Year'!$A:$A,0),MONTH($B$6)+1)} -> 0.02564 | K64: =IF($E$11=39,$G$11,0) -> 0 | L64: =_39_Year_Post_CS12[[#This Row],[Adj Basis]]*_39_Year_Post_CS12[[#This Row],[39-Year Rate]] -> 0 | M64: =M63+_39_Year_Post_CS12[[#This Row],[Annual Depreciation]] -> 0
A65: =A64+1 -> 11 | B65: =B64+1 -> 2034 | C65: {=INDEX('39-Year'!$A$1:$M$43,MATCH(_27.5_Year_Original11[[#This Row],[Year No.]],'39-Year'!$A:$A,0),MONTH($B$6)+1)} -> 0.02564 | D65: =IF($E$11=39,$D$11,0) -> 0 | E65: =_27.5_Year_Original11[[#This Row],[Original Basis]]*_27.5_Year_Original11[[#This Row],[39-Year Rate]] -> 0 | F65: =F64+_27.5_Year_Original11[[#This Row],[Annual Depreciation]] -> 0 | H65: =H64+1 -> 11 | I65: =I64+1 -> 2034 | J65: {=INDEX('39-Year'!$A$1:$M$43,MATCH(_39_Year_Post_CS12[[#This Row],[Year No.]],'39-Year'!$A:$A,0),MONTH($B$6)+1)} -> 0.02564 | K65: =IF($E$11=39,$G$11,0) -> 0 | L65: =_39_Year_Post_CS12[[#This Row],[Adj Basis]]*_39_Year_Post_CS12[[#This Row],[39-Year Rate]] -> 0 | M65: =M64+_39_Year_Post_CS12[[#This Row],[Annual Depreciation]] -> 0
A66: =A65+1 -> 12 | B66: =B65+1 -> 2035 | C66: {=INDEX('39-Year'!$A$1:$M$43,MATCH(_27.5_Year_Original11[[#This Row],[Year No.]],'39-Year'!$A:$A,0),MONTH($B$6)+1)} -> 0.02564 | D66: =IF($E$11=39,$D$11,0) -> 0 | E66: =_27.5_Year_Original11[[#This Row],[Original Basis]]*_27.5_Year_Original11[[#This Row],[39-Year Rate]] -> 0 | F66: =F65+_27.5_Year_Original11[[#This Row],[Annual Depreciation]] -> 0 | H66: =H65+1 -> 12 | I66: =I65+1 -> 2035 | J66: {=INDEX('39-Year'!$A$1:$M$43,MATCH(_39_Year_Post_CS12[[#This Row],[Year No.]],'39-Year'!$A:$A,0),MONTH($B$6)+1)} -> 0.02564 | K66: =IF($E$11=39,$G$11,0) -> 0 | L66: =_39_Year_Post_CS12[[#This Row],[Adj Basis]]*_39_Year_Post_CS12[[#This Row],[39-Year Rate]] -> 0 | M66: =M65+_39_Year_Post_CS12[[#This Row],[Annual Depreciation]] -> 0
A67: =A66+1 -> 13 | B67: =B66+1 -> 2036 | C67: {=INDEX('39-Year'!$A$1:$M$43,MATCH(_27.5_Year_Original11[[#This Row],[Year No.]],'39-Year'!$A:$A,0),MONTH($B$6)+1)} -> 0.02564 | D67: =IF($E$11=39,$D$11,0) -> 0 | E67: =_27.5_Year_Original11[[#This Row],[Original Basis]]*_27.5_Year_Original11[[#This Row],[39-Year Rate]] -> 0 | F67: =F66+_27.5_Year_Original11[[#This Row],[Annual Depreciation]] -> 0 | H67: =H66+1 -> 13 | I67: =I66+1 -> 2036 | J67: {=INDEX('39-Year'!$A$1:$M$43,MATCH(_39_Year_Post_CS12[[#This Row],[Year No.]],'39-Year'!$A:$A,0),MONTH($B$6)+1)} -> 0.02564 | K67: =IF($E$11=39,$G$11,0) -> 0 | L67: =_39_Year_Post_CS12[[#This Row],[Adj Basis]]*_39_Year_Post_CS12[[#This Row],[39-Year Rate]] -> 0 | M67: =M66+_39_Year_Post_CS12[[#This Row],[Annual Depreciation]] -> 0
... A83: =A82+1 -> 29 | B83: =B82+1 -> 2052 | C83: {=INDEX('39-Year'!$A$1:$M$43,MATCH(_27.5_Year_Original11[[#This Row],[Year No.]],'39-Year'!$A:$A,0),MONTH($B$6)+1)} -> 0.02564 | D83: =IF($E$11=39,$D$11,0) -> 0 | E83: =_27.5_Year_Original11[[#This Row],[Original Basis]]*_27.5_Year_Original11[[#This Row],[39-Year Rate]] -> 0 | F83: =F82+_27.5_Year_Original11[[#This Row],[Annual Depreciation]] -> 0 | H83: =H82+1 -> 29 | I83: =I82+1 -> 2052 | J83: {=INDEX('39-Year'!$A$1:$M$43,MATCH(_39_Year_Post_CS12[[#This Row],[Year No.]],'39-Year'!$A:$A,0),MONTH($B$6)+1)} -> 0.02564 | K83: =IF($E$11=39,$G$11,0) -> 0 | L83: =_39_Year_Post_CS12[[#This Row],[Adj Basis]]*_39_Year_Post_CS12[[#This Row],[39-Year Rate]] -> 0 | M83: =M82+_39_Year_Post_CS12[[#This Row],[Annual Depreciation]] -> 0
A84: =A83+1 -> 30 | B84: =B83+1 -> 2053 | C84: {=INDEX('39-Year'!$A$1:$M$43,MATCH(_27.5_Year_Original11[[#This Row],[Year No.]],'39-Year'!$A:$A,0),MONTH($B$6)+1)} -> 0.02564 | D84: =IF($E$11=39,$D$11,0) -> 0 | E84: =_27.5_Year_Original11[[#This Row],[Original Basis]]*_27.5_Year_Original11[[#This Row],[39-Year Rate]] -> 0 | F84: =SUM(E84+F83) -> 0 | H84: =H83+1 -> 30 | I84: =I83+1 -> 2053 | J84: {=INDEX('39-Year'!$A$1:$M$43,MATCH(_39_Year_Post_CS12[[#This Row],[Year No.]],'39-Year'!$A:$A,0),MONTH($B$6)+1)} -> 0.02564 | K84: =IF($E$11=39,$G$11,0) -> 0 | L84: =_39_Year_Post_CS12[[#This Row],[Adj Basis]]*_39_Year_Post_CS12[[#This Row],[39-Year Rate]] -> 0 | M84: =SUM(L84+M83) -> 0
A85: =A84+1 -> 31 | B85: =B84+1 -> 2054 | C85: {=INDEX('39-Year'!$A$1:$M$43,MATCH(_27.5_Year_Original11[[#This Row],[Year No.]],'39-Year'!$A:$A,0),MONTH($B$6)+1)} -> 0.02564 | D85: =IF($E$11=39,$D$11,0) -> 0 | E85: =_27.5_Year_Original11[[#This Row],[Original Basis]]*_27.5_Year_Original11[[#This Row],[39-Year Rate]] -> 0 | F85: =SUM(E85+F84) -> 0 | H85: =H84+1 -> 31 | I85: =I84+1 -> 2054 | J85: {=INDEX('39-Year'!$A$1:$M$43,MATCH(_39_Year_Post_CS12[[#This Row],[Year No.]],'39-Year'!$A:$A,0),MONTH($B$6)+1)} -> 0.02564 | K85: =IF($E$11=39,$G$11,0) -> 0 | L85: =_39_Year_Post_CS12[[#This Row],[Adj Basis]]*_39_Year_Post_CS12[[#This Row],[39-Year Rate]] -> 0 | M85: =SUM(L85+M84) -> 0
A86: =A85+1 -> 32 | B86: =B85+1 -> 2055 | C86: {=INDEX('39-Year'!$A$1:$M$43,MATCH(_27.5_Year_Original11[[#This Row],[Year No.]],'39-Year'!$A:$A,0),MONTH($B$6)+1)} -> 0.02564 | D86: =IF($E$11=39,$D$11,0) -> 0 | E86: =_27.5_Year_Original11[[#This Row],[Original Basis]]*_27.5_Year_Original11[[#This Row],[39-Year Rate]] -> 0 | F86: =SUM(E86+F85) -> 0 | H86: =H85+1 -> 32 | I86: =I85+1 -> 2055 | J86: {=INDEX('39-Year'!$A$1:$M$43,MATCH(_39_Year_Post_CS12[[#This Row],[Year No.]],'39-Year'!$A:$A,0),MONTH($B$6)+1)} -> 0.02564 | K86: =IF($E$11=39,$G$11,0) -> 0 | L86: =_39_Year_Post_CS12[[#This Row],[Adj Basis]]*_39_Year_Post_CS12[[#This Row],[39-Year Rate]] -> 0 | M86: =SUM(L86+M85) -> 0
A87: =A86+1 -> 33 | B87: =B86+1 -> 2056 | C87: {=INDEX('39-Year'!$A$1:$M$43,MATCH(_27.5_Year_Original11[[#This Row],[Year No.]],'39-Year'!$A:$A,0),MONTH($B$6)+1)} -> 0.02564 | D87: =IF($E$11=39,$D$11,0) -> 0 | E87: =_27.5_Year_Original11[[#This Row],[Original Basis]]*_27.5_Year_Original11[[#This Row],[39-Year Rate]] -> 0 | F87: =SUM(E87+F86) -> 0 | H87: =H86+1 -> 33 | I87: =I86+1 -> 2056 | J87: {=INDEX('39-Year'!$A$1:$M$43,MATCH(_39_Year_Post_CS12[[#This Row],[Year No.]],'39-Year'!$A:$A,0),MONTH($B$6)+1)} -> 0.02564 | K87: =IF($E$11=39,$G$11,0) -> 0 | L87: =_39_Year_Post_CS12[[#This Row],[Adj Basis]]*_39_Year_Post_CS12[[#This Row],[39-Year Rate]] -> 0 | M87: =SUM(L87+M86) -> 0
A88: =A87+1 -> 34 | B88: =B87+1 -> 2057 | C88: {=INDEX('39-Year'!$A$1:$M$43,MATCH(_27.5_Year_Original11[[#This Row],[Year No.]],'39-Year'!$A:$A,0),MONTH($B$6)+1)} -> 0.02564 | D88: =IF($E$11=39,$D$11,0) -> 0 | E88: =_27.5_Year_Original11[[#This Row],[Original Basis]]*_27.5_Year_Original11[[#This Row],[39-Year Rate]] -> 0 | F88: =SUM(E88+F87) -> 0 | H88: =H87+1 -> 34 | I88: =I87+1 -> 2057 | J88: {=INDEX('39-Year'!$A$1:$M$43,MATCH(_39_Year_Post_CS12[[#This Row],[Year No.]],'39-Year'!$A:$A,0),MONTH($B$6)+1)} -> 0.02564 | K88: =IF($E$11=39,$G$11,0) -> 0 | L88: =_39_Year_Post_CS12[[#This Row],[Adj Basis]]*_39_Year_Post_CS12[[#This Row],[39-Year Rate]] -> 0 | M88: =SUM(L88+M87) -> 0
A89: =A88+1 -> 35 | B89: =B88+1 -> 2058 | C89: {=INDEX('39-Year'!$A$1:$M$43,MATCH(_27.5_Year_Original11[[#This Row],[Year No.]],'39-Year'!$A:$A,0),MONTH($B$6)+1)} -> 0.02564 | D89: =IF($E$11=39,$D$11,0) -> 0 | E89: =_27.5_Year_Original11[[#This Row],[Original Basis]]*_27.5_Year_Original11[[#This Row],[39-Year Rate]] -> 0 | F89: =SUM(E89+F88) -> 0 | H89: =H88+1 -> 35 | I89: =I88+1 -> 2058 | J89: {=INDEX('39-Year'!$A$1:$M$43,MATCH(_39_Year_Post_CS12[[#This Row],[Year No.]],'39-Year'!$A:$A,0),MONTH($B$6)+1)} -> 0.02564 | K89: =IF($E$11=39,$G$11,0) -> 0 | L89: =_39_Year_Post_CS12[[#This Row],[Adj Basis]]*_39_Year_Post_CS12[[#This Row],[39-Year Rate]] -> 0 | M89: =SUM(L89+M88) -> 0
A90: =A89+1 -> 36 | B90: =B89+1 -> 2059 | C90: {=INDEX('39-Year'!$A$1:$M$43,MATCH(_27.5_Year_Original11[[#This Row],[Year No.]],'39-Year'!$A:$A,0),MONTH($B$6)+1)} -> 0.02564 | D90: =IF($E$11=39,$D$11,0) -> 0 | E90: =_27.5_Year_Original11[[#This Row],[Original Basis]]*_27.5_Year_Original11[[#This Row],[39-Year Rate]] -> 0 | F90: =SUM(E90+F89) -> 0 | H90: =H89+1 -> 36 | I90: =I89+1 -> 2059 | J90: {=INDEX('39-Year'!$A$1:$M$43,MATCH(_39_Year_Post_CS12[[#This Row],[Year No.]],'39-Year'!$A:$A,0),MONTH($B$6)+1)} -> 0.02564 | K90: =IF($E$11=39,$G$11,0) -> 0 | L90: =_39_Year_Post_CS12[[#This Row],[Adj Basis]]*_39_Year_Post_CS12[[#This Row],[39-Year Rate]] -> 0 | M90: =SUM(L90+M89) -> 0
A91: =A90+1 -> 37 | B91: =B90+1 -> 2060 | C91: {=INDEX('39-Year'!$A$1:$M$43,MATCH(_27.5_Year_Original11[[#This Row],[Year No.]],'39-Year'!$A:$A,0),MONTH($B$6)+1)} -> 0.02564 | D91: =IF($E$11=39,$D$11,0) -> 0 | E91: =_27.5_Year_Original11[[#This Row],[Original Basis]]*_27.5_Year_Original11[[#This Row],[39-Year Rate]] -> 0 | F91: =SUM(E91+F90) -> 0 | H91: =H90+1 -> 37 | I91: =I90+1 -> 2060 | J91: {=INDEX('39-Year'!$A$1:$M$43,MATCH(_39_Year_Post_CS12[[#This Row],[Year No.]],'39-Year'!$A:$A,0),MONTH($B$6)+1)} -> 0.02564 | K91: =IF($E$11=39,$G$11,0) -> 0 | L91: =_39_Year_Post_CS12[[#This Row],[Adj Basis]]*_39_Year_Post_CS12[[#This Row],[39-Year Rate]] -> 0 | M91: =SUM(L91+M90) -> 0
A92: =A91+1 -> 38 | B92: =B91+1 -> 2061 | C92: {=INDEX('39-Year'!$A$1:$M$43,MATCH(_27.5_Year_Original11[[#This Row],[Year No.]],'39-Year'!$A:$A,0),MONTH($B$6)+1)} -> 0.02564 | D92: =IF($E$11=39,$D$11,0) -> 0 | E92: =_27.5_Year_Original11[[#This Row],[Original Basis]]*_27.5_Year_Original11[[#This Row],[39-Year Rate]] -> 0 | F92: =SUM(E92+F91) -> 0 | H92: =H91+1 -> 38 | I92: =I91+1 -> 2061 | J92: {=INDEX('39-Year'!$A$1:$M$43,MATCH(_39_Year_Post_CS12[[#This Row],[Year No.]],'39-Year'!$A:$A,0),MONTH($B$6)+1)} -> 0.02564 | K92: =IF($E$11=39,$G$11,0) -> 0 | L92: =_39_Year_Post_CS12[[#This Row],[Adj Basis]]*_39_Year_Post_CS12[[#This Row],[39-Year Rate]] -> 0 | M92: =SUM(L92+M91) -> 0
A93: =A92+1 -> 39 | B93: =B92+1 -> 2062 | C93: {=INDEX('39-Year'!$A$1:$M$43,MATCH(_27.5_Year_Original11[[#This Row],[Year No.]],'39-Year'!$A:$A,0),MONTH($B$6)+1)} -> 0.02564 | D93: =IF($E$11=39,$D$11,0) -> 0 | E93: =_27.5_Year_Original11[[#This Row],[Original Basis]]*_27.5_Year_Original11[[#This Row],[39-Year Rate]] -> 0 | F93: =SUM(E93+F92) -> 0 | H93: =H92+1 -> 39 | I93: =I92+1 -> 2062 | J93: {=INDEX('39-Year'!$A$1:$M$43,MATCH(_39_Year_Post_CS12[[#This Row],[Year No.]],'39-Year'!$A:$A,0),MONTH($B$6)+1)} -> 0.02564 | K93: =IF($E$11=39,$G$11,0) -> 0 | L93: =_39_Year_Post_CS12[[#This Row],[Adj Basis]]*_39_Year_Post_CS12[[#This Row],[39-Year Rate]] -> 0 | M93: =SUM(L93+M92) -> 0
A94: =A93+1 -> 40 | B94: =B93+1 -> 2063 | C94: {=INDEX('39-Year'!$A$1:$M$43,MATCH(_27.5_Year_Original11[[#This Row],[Year No.]],'39-Year'!$A:$A,0),MONTH($B$6)+1)} -> 0.00107 | D94: =IF($E$11=39,$D$11,0) -> 0 | E94: =_27.5_Year_Original11[[#This Row],[Original Basis]]*_27.5_Year_Original11[[#This Row],[39-Year Rate]] -> 0 | F94: =SUM(E94+F93) -> 0 | H94: =H93+1 -> 40 | I94: =I93+1 -> 2063 | J94: {=INDEX('39-Year'!$A$1:$M$43,MATCH(_39_Year_Post_CS12[[#This Row],[Year No.]],'39-Year'!$A:$A,0),MONTH($B$6)+1)} -> 0.00107 | K94: =IF($E$11=39,$G$11,0) -> 0 | L94: =_39_Year_Post_CS12[[#This Row],[Adj Basis]]*_39_Year_Post_CS12[[#This Row],[39-Year Rate]] -> 0 | M94: =SUM(L94+M93) -> 0

Sheet Definitions
A1: Bonus | G1: 5-Yr | H1: 15-Yr | I1: Total
A2: 37145 | B2: 37746 | C2: 0.3 | E2: --
A3: 37747 | B3: 38352 | C3: 0.5 | E3: Custom | F3: =E3 -> Custom | G3: 0 | H3: 0 | I3: =SUM(G3:H3) -> 0 | K3: --
A4: 38353 | B4: 39447 | C4: 0 | E4: Single Family Residence | F4: =E4 -> Single Family Residence | G4: 0.12 | H4: 0.08 | I4: =SUM(G4:H4) -> 0.2 | K4: Custom
A5: 39448 | B5: 40429 | C5: 0.5 | E5: Duplex | F5: =E5 -> Duplex | G5: 0.14 | H5: 0.08 | I5: =SUM(G5:H5) -> 0.22 | K5: Single Family Residence
A6: 40430 | B6: 40908 | C6: 1 | E6: Triplex | F6: =E6 -> Triplex | G6: 0.14 | H6: 0.08 | I6: =SUM(G6:H6) -> 0.22 | K6: Duplex
A7: 40909 | B7: 43005 | C7: 0.5 | E7: 4-Plex | F7: =E7 -> 4-Plex | G7: 0.14 | H7: 0.08 | I7: =SUM(G7:H7) -> 0.22 | K7: Triplex
A8: 43006 | B8: 44926 | C8: 1 | E8: Townhome | F8: =E8 -> Townhome | G8: 0.12 | H8: 0.08 | I8: =SUM(G8:H8) -> 0.2 | K8: 4-Plex
A9: 44927 | B9: 45291 | C9: 0.8 | E9: Condo | F9: =E9 -> Condo | G9: 0.17 | H9: 0 | I9: =SUM(G9:H9) -> 0.17 | K9: Townhome
A10: 45292 | B10: 45657 | C10: 0.6 | E10: Apartment | F10: =E10 -> Apartment | G10: 0.14 | H10: 0.08 | I10: =SUM(G10:H10) -> 0.22 | K10: Condo
A11: 45658 | B11: 45676 | C11: 0.4 | E11: Mixed-Use | F11: =E11 -> Mixed-Use | G11: 0.14 | H11: 0.08 | I11: =SUM(G11:H11) -> 0.22 | K11: Apartment
A12: 45677 | B12: 47483 | C12: 1 | E12: STR Single Family Residence | F12: =E12 -> STR Single Family Residence | G12: 0.12 | H12: 0.08 | I12: =SUM(G12:H12) -> 0.2 | K12: Mixed-Use
E13: STR Condo | F13: =E13 -> STR Condo | G13: 0.17 | H13: 0 | I13: =SUM(G13:H13) -> 0.17 | K13: STR Single Family Residence
E14: Single Family Residence Economy | F14: Single Family Residence | G14: 0.12 | H14: 0.08 | I14: =SUM(G14:H14) -> 0.2 | K14: STR Condo
E15: STR Single Family Residence Economy | F15: STR Single Family Residence | G15: 0.12 | H15: 0.08 | I15: =SUM(G15:H15) -> 0.2 | K15: Assisted Living Facility
E16: Single Family Residence Builders Choice | F16: Single Family Residence | G16: 0.14 | H16: 0.1 | I16: =SUM(G16:H16) -> 0.24 | K16: Grocery Store
E17: STR Single Family Residence Builders Choice | F17: STR Single Family Residence | G17: 0.14 | H17: 0.1 | I17: =SUM(G17:H17) -> 0.24 | K17: Medical Center
E18: Single Family Residence Custom | F18: Single Family Residence | G18: 0.16 | H18: 0.12 | I18: =SUM(G18:H18) -> 0.28 | K18: Office Condo
E19: STR Single Family Residence Custom | F19: STR Single Family Residence | G19: 0.16 | H19: 0.12 | I19: =SUM(G19:H19) -> 0.28 | K19: Office Building
E20: Condo | F20: Condo | G20: 0.17 | H20: 0 | I20: =SUM(G20:H20) -> 0.17 | K20: Restaurant
E21: STR Condo | F21: STR Condo | G21: 0.17 | H21: 0 | I21: =SUM(G21:H21) -> 0.17 | K21: Warehouse
E22: Multifamily Residence Economy | F22: Multifamily Residence | G22: 0.14 | H22: 0.08 | I22: =SUM(G22:H22) -> 0.22
E23: Multifamily Residence Builders Choice | F23: Multifamily Residence | G23: 0.16 | H23: 0.1 | I23: =SUM(G23:H23) -> 0.26
E24: Assisted Living Facility | F24: Assisted Living Facility | G24: 0.15 | H24: 0.1 | I24: =SUM(G24:H24) -> 0.25
E25: Auto Repair | F25: Auto Repair | G25: 0.15 | H25: 0.1 | I25: =SUM(G25:H25) -> 0.25
E26: Car Wash | F26: Car Wash | G26: 0.05 | H26: 0.95 | I26: =SUM(G26:H26) -> 1
E27: Daycare Facility | F27: Daycare Facility | G27: 0.1 | H27: 0.1 | I27: =SUM(G27:H27) -> 0.2
E28: Fitness Center | F28: Fitness Center | G28: 0.2 | H28: 0.05 | I28: =SUM(G28:H28) -> 0.25
E29: Grocery Store | F29: Grocery Store | G29: 0.2 | H29: 0.15 | I29: =SUM(G29:H29) -> 0.35
E30: Hotel - Full Service | F30: Hotel | G30: 0.19 | H30: 0.06 | I30: =SUM(G30:H30) -> 0.25
E31: Hotel - Ltd Service | F31: Hotel | G31: 0.17 | H31: 0.1 | I31: =SUM(G31:H31) -> 0.27
E32: Strip Mall | F32: Strip Mall | G32: 0.12 | H32: 0.13 | I32: =SUM(G32:H32) -> 0.25
E33: Marina | F33: Marina | G33: 0.15 | H33: 0.15 | I33: =SUM(G33:H33) -> 0.3
... E44: Warehouse Facility | F44: Warehouse | G44: 0.02 | H44: 0.12 | I44: =SUM(G44:H44) -> 0.14

Sheet Client Summary
A1: #VALUE!
A7: US Tax Advisors Group, Inc. Modeling Calculation
A9: Enclosed is the result of a US Tax Advisors Group, Inc. (USTAGI) Construction Cost Modeling Calculation which utilizes a national construction cost database to model the building’s quantities and costs. The data is then statistically segregated, as appropriate, between section 1245 and 1250 property.
C12: Property Address: | G12: 861 E 800 S, Salt Lake City, UT 84102
C13: Date Placed in Service: | G13: 45292 | M13: Tax Year | N13: 2025
C14: Cost Basis: | G14: 0
C15: Land Allocation: | G15: 0
C16: Building Basis: | G16: =G14-G15 -> 0
C17: Improvements included in the Study: | G17: 0
C18: Basis for Cost Segregation: | G18: =G16+G17 -> 0
C19: ="Accumulated Depreciation as of 12/31/"&'Study Data'!$B$5-1&":" -> Accumulated Depreciation as of 12/31/2024: | G19: 0
C20: Occupancy Type: | G20: Residential
C21: Building Use: | G21: Single Family Residence
A24: Based on these results, the Federal Tax Depreciation Schedule should be revised as follows:
A25: Asset ID | B25: Property Description | E25: Date Acquired | F25: Basis | G25: Life (Years) | H25: Depr Method | I25: Conv | J25: ="Accumulated Depreciation as of 12/31/"&'Study Data'!$B$5-1 -> Accumulated Depreciation as of 12/31/2024 | L25: Depreciation Adjustment
A26: 1 | B26: Building | E26: =+$G$13 -> 45292 | F26: =_xlfn.IFNA(ROUND(Calculator!C5,0),0) -> 0 | G26: =IF($G$20="Residential",27.5,39) -> 27.5 | H26: SL | I26: Mid-Month | J26: =ROUND(IF(F26=0,0,'Study Data'!K11),0) -> 0 | L26: =J26-G19 -> 0
A27: 1.1 | B27: Asset Class 57.0 - Distributive Trades and Services | E27: =+$G$13 -> 45292 | F27: =_xlfn.IFNA(ROUND(Calculator!C7,0),0) -> 0 | G27: 5 | H27: 200DB | I27: Half-Year | J27: =ROUND(IF(F27=0,0,'Study Data'!K12),0) -> 0 | L27: =J27 -> 0
A28: 1.2 | B28: Asset Class 0.11 - Office Furniture, Fixtures and Equipment | E28: =+$G$13 -> 45292 | F28: 0 | G28: 7 | H28: 200DB | I28: Half-Year | J28: =ROUND(IF(F28=0,0,'Study Data'!K13),0) -> 0 | L28: =J28 -> 0
A29: 1.3 | B29: Asset Class 0.30 - Land Improvements | E29: =+$G$13 -> 45292 | F29: =_xlfn.IFNA(ROUND(Calculator!C6,0),0) -> 0 | G29: 15 | H29: 150DB | I29: Half-Year | J29: =ROUND(IF(F29=0,0,'Study Data'!K14),0) -> 0 | L29: =J29 -> 0
B30: Totals | F30: =SUM(F26:F29) -> 0 | J30: =SUM(J26:K29) -> 0 | L30: =SUM(L26:M29) -> 0
A32: This Construction Cost Modeling Calculation along with the Schedules represent the Cost Segregation Report. If the property was placed into service in a prior tax year you will need to file Form 3115 along with the Form 3115 Attachment.
M35: =SUM(F27:F29) -> 0
A38: Form 3115 - Attachment
A40: For Property Located at: | E40: =G12 -> 861 E 800 S, Salt Lake City, UT 84102
A41: Part II: Information For All Requests:
A42: Question 14:
A43: a) | B43: The following items were reclassified as follows:
A45: Item | H45: Date Placed in Service | J45: Original Basis
A46: Asset Class 57.0 - Distributive Trades and Services | H46: =$G$13 -> 45292 | J46: =F27 -> 0
A47: Asset Class 0.11 - Office Furniture, Fixtures, & Equipment | H47: =$G$13 -> 45292 | J47: =F28 -> 0
A48: Asset Class 0.30 - Land Improvements | H48: =$G$13 -> 45292 | J48: =F29 -> 0
A50: b) | B50: The property was currently being depreciated as Section 1250 property, and part of the building's original basis.
A51: c) | B51: The applicant proposes to reclassify the above property as personal property under 26 CFR 1.168.
A52: d) | B52: The applicant's present overall method of accounting is the | H52: Cash Method
A54: Question 15(a):
A55: The applicant's trade or business is: | F55: =IF($F$56=531110,"Lessors of Residential Buildings and Dwellings","Lessors of Nonresidential Buildings") -> Lessors of Residential Buildings and Dwellings
A56: Business Activity Code: | F56: =IF($G$20="Residential",531110,531120) -> 531110
A58: Question 16:
A59: a) | B59: Under its present method, the Applicant is claiming less depreciation than allowable on certain assets. The code section which the Applicant will depreciate or amortize
B60: property is under §168. Major categories of expenditures examined are below:
B62: Personal Property
B64: The Applicant has depreciated personal property such as carpeting, vinyl composite tile flooring, raised flooring, dedicated special purpose plumbing fixtures, dedicated
B65: special purpose electrical wiring and fixtures, decorative lighting, millwork and cabinetry, countertops as either residential real property with a 27.5-year GDS or
B66: nonresidential real property with a 39-year GDS. According to Asset class 57.0, Distributive Trades and Services these assets are appropriately reassigned a recovery
B67: period of 5-years GDS (half-year convention using 200 percent declining balance method). Additional first-year deprecation allowance as provided by §168(k) will apply
B68: for qualified assets.
B70: General Land Improvements
B72: The Applicant has depreciated land improvements such as site lights, site stormwater drainage, paving and hardscaping, and landscaping as either residential real
B73: property with a 27.5-year GDS or nonresidential real property with a 39-year GDS. According to Asset class 00.3 Land Improvements, these assets are appropriately
B74: reassigned a recovery period of 15-years GDS (half-year convention using 150 percent declining balance method). Additional first-year deprecation allowance as
B75: provided by §168(k) will apply for qualified assets.
A77: b) | B77: See response to Question 16a, above.
A79: Part IV: Section 481(a) Adjustment
A80: Question 26
A81: Deducting, under Section 481(a), the catchup depreciation for the assets being changed are as follows:
B83: Item | E83: Catchup Depreciation
B84: 5-Year Property | E84: =ROUND(-J27,0) -> 0
B85: 7-Year Property | E85: =ROUND(-J28,0) -> 0
B86: 15-Year Property | E86: =ROUND(-J29,0) -> 0
B87: 27.5-Year Property | E87: =ROUND(G19-J26,0) -> 0
B88: Total 481(a) | E88: =+SUM(E84:F87) -> 0
A90: Schedule E: Change In Depreciation or Amortization
A91: Question 4(a): | D91: See response to Question 14, above.
D92: The property is used as a | G92: =G21 -> Single Family Residence
A94: Question 5: | D94: See response to Question 14, above.
A96: Question 7:
A97: a) | B97: The property is presently being depreciated under Code Section 167 or 168.
A98: b) | B98: The current applicable asset classes used include: See response to Question 14, above.
A99: c) | B99: Based on the facts and circumstances, each item was appropriately classified under MACRS.
A100: d) | F100: Life (Yrs.) | G100: Method | H100: Convention
B101: 57.00 Distributive Trades and Services | F101: 5 | G101: 200DB | H101: Half-Year
B102: 0.11 Office Furniture, Fixtures, and Equipment | F102: 7 | G102: 200DB | H102: Half-Year
B103: 0.3 Land Improvements | F103: 15 | G103: 150DB | H103: Half-Year
A104: e) | B104: See response to Question 7d, above.
A105: f) | B105: See response to Question 7d, above.
A106: g) | B106: Yes, additional first-year depreciation allowance as provided by §168(k) will apply.
A107: h) | B107: The property will be in various multiple asset accounts.

Sheet 27.5 Estimate
B1: #VALUE!
B7: Cost Segregation Estimate
C9: Property Address: | G9: ='Client Summary'!G12 -> 861 E 800 S, Salt Lake City, UT 84102
C10: Building Use: | G10: =_xlfn.XLOOKUP('Client Summary'!$G$21,Definitions!$E$2:$E$35,Definitions!$F$2:$F$35,0,0,1) -> Single Family Residence
C11: Date Placed in Service: | F11: ='Client Summary'!G13 -> 45292
C12: Cost Basis: | G12: ='Client Summary'!G14 -> 0
C13: Land Allocation: | D13: =IFERROR(G13/G12,"") | E13: Per Depreciation Schedule | G13: ='Client Summary'!G15 -> 0
C14: Building Basis: | G14: ='Client Summary'!G16 -> 0
C15: Improvements included in the Study: | G15: ='Client Summary'!G17 -> 0
C16: Basis for Cost Segregation: | G16: ='Client Summary'!G18 -> 0
C17: ="Accumulated Depreciation as of 12/31/"&'Study Data'!$B$5-1&":" -> Accumulated Depreciation as of 12/31/2024: | G17: ='Client Summary'!G19 -> 0
C19: Total Accelerated: | G19: =SUM($C$56:$E$56) -> 0
C20: Tax Savings Benefit at a 40% Income Tax Rate: | G20: =$G$19*40% -> 0
C22: Estimated Additional Depreciation Expense: | G22: =SUMIFS($G$27:$G$55,$B$27:$B$55,"<"&'Client Summary'!$N$13)-IF($G$17=0,SUMIFS($H$27:$H$55,$B$27:$B$55,"<"&'Client Summary'!$N$13),'27.5 Estimate'!$G$17) -> 0
C23: Tax Savings Benefit at a 40% Income Tax Rate: | G23: =$G$22*40% -> 0
B25: USTAGI estimates the following results of the Cost Segregation Study:
B26: Tax Year | C26: 5 Years Depr. with CSS | D26: 7 Years Depr. with CSS | E26: 15 Years Depr. with CSS | F26: 27.5 Years Depr. with CSS | G26: Depr. with CSS | H26: Depr. without CSS
B27: =YEAR($F$11) -> 2024 | C27: =IF('Client Summary'!$G$20="Residential",'Study Data'!T21,0) -> 0 | D27: =IF('Client Summary'!$G$20="Residential",'Study Data'!AA21,0) -> 0 | E27: =IF('Client Summary'!$G$20="Residential",'Study Data'!AH21,0) -> 0 | F27: ='Study Data'!L21 -> 0 | G27: =SUM(C27:F27) -> 0 | H27: ='Study Data'!E21 -> 0
B28: =B27+1 -> 2025 | C28: =IF('Client Summary'!$G$20="Residential",'Study Data'!S22,0) -> 0 | D28: =IF('Client Summary'!$G$20="Residential",'Study Data'!Z22,0) -> 0 | E28: =IF('Client Summary'!$G$20="Residential",'Study Data'!AG22,0) -> 0 | F28: ='Study Data'!L22 -> 0 | G28: =SUM(C28:F28) -> 0 | H28: ='Study Data'!E22 -> 0
B29: =B28+1 -> 2026 | C29: =IF('Client Summary'!$G$20="Residential",'Study Data'!S23,0) -> 0 | D29: =IF('Client Summary'!$G$20="Residential",'Study Data'!Z23,0) -> 0 | E29: =IF('Client Summary'!$G$20="Residential",'Study Data'!AG23,0) -> 0 | F29: ='Study Data'!L23 -> 0 | G29: =SUM(C29:F29) -> 0 | H29: ='Study Data'!E23 -> 0
B30: =B29+1 -> 2027 | C30: =IF('Client Summary'!$G$20="Residential",'Study Data'!S24,0) -> 0 | D30: =IF('Client Summary'!$G$20="Residential",'Study Data'!Z24,0) -> 0 | E30: =IF('Client Summary'!$G$20="Residential",'Study Data'!AG24,0) -> 0 | F30: ='Study Data'!L24 -> 0 | G30: =SUM(C30:F30) -> 0 | H30: ='Study Data'!E24 -> 0
B31: =B30+1 -> 2028 | C31: =IF('Client Summary'!$G$20="Residential",'Study Data'!S25,0) -> 0 | D31: =IF('Client Summary'!$G$20="Residential",'Study Data'!Z25,0) -> 0 | E31: =IF('Client Summary'!$G$20="Residential",'Study Data'!AG25,0) -> 0 | F31: ='Study Data'!L25 -> 0 | G31: =SUM(C31:F31) -> 0 | H31: ='Study Data'!E25 -> 0
B32: =B31+1 -> 2029 | C32: =IF('Client Summary'!$G$20="Residential",'Study Data'!S26,0) -> 0 | D32: =IF('Client Summary'!$G$20="Residential",'Study Data'!Z26,0) -> 0 | E32: =IF('Client Summary'!$G$20="Residential",'Study Data'!AG26,0) -> 0 | F32: ='Study Data'!L26 -> 0 | G32: =SUM(C32:F32) -> 0 | H32: ='Study Data'!E26 -> 0
B33: =B32+1 -> 2030 | D33: =IF('Client Summary'!$G$20="Residential",'Study Data'!Z27,0) -> 0 | E33: =IF('Client Summary'!$G$20="Residential",'Study Data'!AG27,0) -> 0 | F33: ='Study Data'!L27 -> 0 | G33: =SUM(C33:F33) -> 0 | H33: ='Study Data'!E27 -> 0
B34: =B33+1 -> 2031 | D34: =IF('Client Summary'!$G$20="Residential",'Study Data'!Z28,0) -> 0 | E34: =IF('Client Summary'!$G$20="Residential",'Study Data'!AG28,0) -> 0 | F34: ='Study Data'!L28 -> 0 | G34: =SUM(C34:F34) -> 0 | H34: ='Study Data'!E28 -> 0
B35: =B34+1 -> 2032 | E35: =IF('Client Summary'!$G$20="Residential",'Study Data'!AG29,0) -> 0 | F35: ='Study Data'!L29 -> 0 | G35: =SUM(C35:F35) -> 0 | H35: ='Study Data'!E29 -> 0
B36: =B35+1 -> 2033 | E36: =IF('Client Summary'!$G$20="Residential",'Study Data'!AG30,0) -> 0 | F36: ='Study Data'!L30 -> 0 | G36: =SUM(C36:F36) -> 0 | H36: ='Study Data'!E30 -> 0
B37: =B36+1 -> 2034 | E37: =IF('Client Summary'!$G$20="Residential",'Study Data'!AG31,0) -> 0 | F37: ='Study Data'!L31 -> 0 | G37: =SUM(C37:F37) -> 0 | H37: ='Study Data'!E31 -> 0
B38: =B37+1 -> 2035 | E38: =IF('Client Summary'!$G$20="Residential",'Study Data'!AG32,0) -> 0 | F38: ='Study Data'!L32 -> 0 | G38: =SUM(C38:F38) -> 0 | H38: ='Study Data'!E32 -> 0
B39: =B38+1 -> 2036 | E39: =IF('Client Summary'!$G$20="Residential",'Study Data'!AG33,0) -> 0 | F39: ='Study Data'!L33 -> 0 | G39: =SUM(C39:F39) -> 0 | H39: ='Study Data'!E33 -> 0
B40: =B39+1 -> 2037 | E40: =IF('Client Summary'!$G$20="Residential",'Study Data'!AG34,0) -> 0 | F40: ='Study Data'!L34 -> 0 | G40: =SUM(C40:F40) -> 0 | H40: ='Study Data'!E34 -> 0
B41: =B40+1 -> 2038 | E41: =IF('Client Summary'!$G$20="Residential",'Study Data'!AG35,0) -> 0 | F41: ='Study Data'!L35 -> 0 | G41: =SUM(C41:F41) -> 0 | H41: ='Study Data'!E35 -> 0
B42: =B41+1 -> 2039 | E42: =IF('Client Summary'!$G$20="Residential",'Study Data'!AG36,0) -> 0 | F42: ='Study Data'!L36 -> 0 | G42: =SUM(C42:F42) -> 0 | H42: ='Study Data'!E36 -> 0
B43: =B42+1 -> 2040 | F43: ='Study Data'!L37 -> 0 | G43: =SUM(C43:F43) -> 0 | H43: ='Study Data'!E37 -> 0
B44: =B43+1 -> 2041 | F44: ='Study Data'!L38 -> 0 | G44: =SUM(C44:F44) -> 0 | H44: ='Study Data'!E38 -> 0
B45: =B44+1 -> 2042 | F45: ='Study Data'!L39 -> 0 | G45: =SUM(C45:F45) -> 0 | H45: ='Study Data'!E39 -> 0
B46: =B45+1 -> 2043 | F46: ='Study Data'!L40 -> 0 | G46: =SUM(C46:F46) -> 0 | H46: ='Study Data'!E40 -> 0
B47: =B46+1 -> 2044 | F47: ='Study Data'!L41 -> 0 | G47: =SUM(C47:F47) -> 0 | H47: ='Study Data'!E41 -> 0
B48: =B47+1 -> 2045 | F48: ='Study Data'!L42 -> 0 | G48: =SUM(C48:F48) -> 0 | H48: ='Study Data'!E42 -> 0
B49: =B48+1 -> 2046 | F49: ='Study Data'!L43 -> 0 | G49: =SUM(C49:F49) -> 0 | H49: ='Study Data'!E43 -> 0
B50: =B49+1 -> 2047 | F50: ='Study Data'!L44 -> 0 | G50: =SUM(C50:F50) -> 0 | H50: ='Study Data'!E44 -> 0
B51: =B50+1 -> 2048 | F51: ='Study Data'!L45 -> 0 | G51: =SUM(C51:F51) -> 0 | H51: ='Study Data'!E45 -> 0
B52: =B51+1 -> 2049 | F52: ='Study Data'!L46 -> 0 | G52: =SUM(C52:F52) -> 0 | H52: ='Study Data'!E46 -> 0
B53: =B52+1 -> 2050 | F53: ='Study Data'!L47 -> 0 | G53: =SUM(C53:F53) -> 0 | H53: ='Study Data'!E47 -> 0
B54: =B53+1 -> 2051 | F54: ='Study Data'!L48 -> 0 | G54: =SUM(C54:F54) -> 0 | H54: ='Study Data'!E48 -> 0
B55: =B54+1 -> 2052 | F55: ='Study Data'!L49 -> 0 | G55: =SUM(C55:F55) -> 0 | H55: ='Study Data'!E49 -> 0
B56: Total | C56: =SUM(C27:C55) -> 0 | D56: =SUM(D27:D55) -> 0 | E56: =SUM(E27:E55) -> 0 | F56: =SUM(F27:F55) -> 0 | G56: =SUM(G27:G55) -> 0 | H56: =SUM(H27:H55) -> 0
B59: US Tax Advisors Group, Inc. | 1220 Rosecrans St., Ste 542, San Diego, CA 92106 | (888) 263-1663 | info@ustagi.com

Sheet 39 Estimate
B1: #VALUE!
B7: Cost Segregation Estimate
C9: Property Address: | G9: ='Client Summary'!G12 -> 861 E 800 S, Salt Lake City, UT 84102
C10: Building Use: | G10: =_xlfn.XLOOKUP('Client Summary'!$G$21,Definitions!$E$2:$E$35,Definitions!$F$2:$F$35,0,0,1) -> Single Family Residence
C11: Date Placed in Service: | F11: ='Client Summary'!G13 -> 45292
C12: Cost Basis: | G12: ='Client Summary'!G14 -> 0
C13: Land Allocation: | D13: =IFERROR(G13/G12,"") | E13: Per Depreciation Schedule | G13: ='Client Summary'!G15 -> 0
C14: Building Basis: | G14: ='Client Summary'!G16 -> 0
C15: Improvements included in the Study: | G15: ='Client Summary'!G17 -> 0
C16: Basis for Cost Segregation: | G16: ='Client Summary'!G18 -> 0
C17: ="Accumulated Depreciation as of 12/31/"&'Study Data'!$B$5-1&":" -> Accumulated Depreciation as of 12/31/2024: | G17: ='Client Summary'!G19 -> 0
C19: Total Accelerated: | G19: =SUM(C68:E68) -> 0
C20: Tax Savings Benefit at a 40% Income Tax Rate: | G20: =G19*40% -> 0
C22: Estimated Additional Depreciation Expense: | G22: =SUMIFS($G$27:$G$66,$B$27:$B$66,"<2025")-IF(G17=0,SUMIFS($H$27:$H$66,$B$27:$B$66,"<2025"),G17) -> 0
C23: Tax Savings Benefit at a 40% Income Tax Rate: | G23: =$G$22*40% -> 0
B25: USTAGI estimates the following results of the Cost Segregation Study:
B26: Tax Year | C26: 5 Years Depr. with CSS | D26: 7 Years Depr. with CSS | E26: 15 Years Depr. with CSS | F26: 39 Years Depr. with CSS | G26: Depr. with CSS | H26: Depr. without CSS
B27: =YEAR($F$11) -> 2024 | C27: =IF('Client Summary'!$G$20="Commercial",'Study Data'!T21,0) -> 0 | D27: =IF('Client Summary'!$G$20="Commercial",'Study Data'!AA21,0) -> 0 | E27: =IF('Client Summary'!$G$20="Commercial",'Study Data'!AH21,0) -> 0 | F27: ='Study Data'!L55 -> 0 | G27: =SUM(C27:F27) -> 0 | H27: ='Study Data'!E55 -> 0
B28: =B27+1 -> 2025 | C28: =IF('Client Summary'!$G$20="Commercial",'Study Data'!S22,0) -> 0 | D28: =IF('Client Summary'!$G$20="Commercial",'Study Data'!Z22,0) -> 0 | E28: =IF('Client Summary'!$G$20="Commercial",'Study Data'!AG22,0) -> 0 | F28: ='Study Data'!L56 -> 0 | G28: =SUM(C28:F28) -> 0 | H28: ='Study Data'!E56 -> 0
B29: =B28+1 -> 2026 | C29: =IF('Client Summary'!$G$20="Commercial",'Study Data'!S23,0) -> 0 | D29: =IF('Client Summary'!$G$20="Commercial",'Study Data'!Z23,0) -> 0 | E29: =IF('Client Summary'!$G$20="Commercial",'Study Data'!AG23,0) -> 0 | F29: ='Study Data'!L57 -> 0 | G29: =SUM(C29:F29) -> 0 | H29: ='Study Data'!E57 -> 0
B30: =B29+1 -> 2027 | C30: =IF('Client Summary'!$G$20="Commercial",'Study Data'!S24,0) -> 0 | D30: =IF('Client Summary'!$G$20="Commercial",'Study Data'!Z24,0) -> 0 | E30: =IF('Client Summary'!$G$20="Commercial",'Study Data'!AG24,0) -> 0 | F30: ='Study Data'!L58 -> 0 | G30: =SUM(C30:F30) -> 0 | H30: ='Study Data'!E58 -> 0
B31: =B30+1 -> 2028 | C31: =IF('Client Summary'!$G$20="Commercial",'Study Data'!S25,0) -> 0 | D31: =IF('Client Summary'!$G$20="Commercial",'Study Data'!Z25,0) -> 0 | E31: =IF('Client Summary'!$G$20="Commercial",'Study Data'!AG25,0) -> 0 | F31: ='Study Data'!L59 -> 0 | G31: =SUM(C31:F31) -> 0 | H31: ='Study Data'!E59 -> 0
B32: =B31+1 -> 2029 | C32: =IF('Client Summary'!$G$20="Commercial",'Study Data'!S26,0) -> 0 | D32: =IF('Client Summary'!$G$20="Commercial",'Study Data'!Z26,0) -> 0 | E32: =IF('Client Summary'!$G$20="Commercial",'Study Data'!AG26,0) -> 0 | F32: ='Study Data'!L60 -> 0 | G32: =SUM(C32:F32) -> 0 | H32: ='Study Data'!E60 -> 0
B33: =B32+1 -> 2030 | D33: =IF('Client Summary'!$G$20="Commercial",'Study Data'!Z27,0) -> 0 | E33: =IF('Client Summary'!$G$20="Commercial",'Study Data'!AG27,0) -> 0 | F33: ='Study Data'!L61 -> 0 | G33: =SUM(C33:F33) -> 0 | H33: ='Study Data'!E61 -> 0
B34: =B33+1 -> 2031 | D34: =IF('Client Summary'!$G$20="Commercial",'Study Data'!Z28,0) -> 0 | E34: =IF('Client Summary'!$G$20="Commercial",'Study Data'!AG28,0) -> 0 | F34: ='Study Data'!L62 -> 0 | G34: =SUM(C34:F34) -> 0 | H34: ='Study Data'!E62 -> 0
B35: =B34+1 -> 2032 | E35: =IF('Client Summary'!$G$20="Commercial",'Study Data'!AG29,0) -> 0 | F35: ='Study Data'!L63 -> 0 | G35: =SUM(C35:F35) -> 0 | H35: ='Study Data'!E63 -> 0
B36: =B35+1 -> 2033 | E36: =IF('Client Summary'!$G$20="Commercial",'Study Data'!AG30,0) -> 0 | F36: ='Study Data'!L64 -> 0 | G36: =SUM(C36:F36) -> 0 | H36: ='Study Data'!E64 -> 0
B37: =B36+1 -> 2034 | E37: =IF('Client Summary'!$G$20="Commercial",'Study Data'!AG31,0) -> 0 | F37: ='Study Data'!L65 -> 0 | G37: =SUM(C37:F37) -> 0 | H37: ='Study Data'!E65 -> 0
B38: =B37+1 -> 2035 | E38: =IF('Client Summary'!$G$20="Commercial",'Study Data'!AG32,0) -> 0 | F38: ='Study Data'!L66 -> 0 | G38: =SUM(C38:F38) -> 0 | H38: ='Study Data'!E66 -> 0
B39: =B38+1 -> 2036 | E39: =IF('Client Summary'!$G$20="Commercial",'Study Data'!AG33,0) -> 0 | F39: ='Study Data'!L67 -> 0 | G39: =SUM(C39:F39) -> 0 | H39: ='Study Data'!E67 -> 0
B40: =B39+1 -> 2037 | E40: =IF('Client Summary'!$G$20="Commercial",'Study Data'!AG34,0) -> 0 | F40: ='Study Data'!L68 -> 0 | G40: =SUM(C40:F40) -> 0 | H40: ='Study Data'!E68 -> 0
B41: =B40+1 -> 2038 | E41: =IF('Client Summary'!$G$20="Commercial",'Study Data'!AG35,0) -> 0 | F41: ='Study Data'!L69 -> 0 | G41: =SUM(C41:F41) -> 0 | H41: ='Study Data'!E69 -> 0
B42: =B41+1 -> 2039 | E42: =IF('Client Summary'!$G$20="Commercial",'Study Data'!AG36,0) -> 0 | F42: ='Study Data'!L70 -> 0 | G42: =SUM(C42:F42) -> 0 | H42: ='Study Data'!E70 -> 0
B43: =B42+1 -> 2040 | F43: ='Study Data'!L71 -> 0 | G43: =SUM(C43:F43) -> 0 | H43: ='Study Data'!E71 -> 0
B44: =B43+1 -> 2041 | F44: ='Study Data'!L72 -> 0 | G44: =SUM(C44:F44) -> 0 | H44: ='Study Data'!E72 -> 0
B45: =B44+1 -> 2042 | F45: ='Study Data'!L73 -> 0 | G45: =SUM(C45:F45) -> 0 | H45: ='Study Data'!E73 -> 0
B46: =B45+1 -> 2043 | F46: ='Study Data'!L74 -> 0 | G46: =SUM(C46:F46) -> 0 | H46: ='Study Data'!E74 -> 0
B47: =B46+1 -> 2044 | F47: ='Study Data'!L75 -> 0 | G47: =SUM(C47:F47) -> 0 | H47: ='Study Data'!E75 -> 0
B48: =B47+1 -> 2045 | F48: ='Study Data'!L76 -> 0 | G48: =SUM(C48:F48) -> 0 | H48: ='Study Data'!E76 -> 0
B49: =B48+1 -> 2046 | F49: ='Study Data'!L77 -> 0 | G49: =SUM(C49:F49) -> 0 | H49: ='Study Data'!E77 -> 0
B50: =B49+1 -> 2047 | F50: ='Study Data'!L78 -> 0 | G50: =SUM(C50:F50) -> 0 | H50: ='Study Data'!E78 -> 0
B51: =B50+1 -> 2048 | F51: ='Study Data'!L79 -> 0 | G51: =SUM(C51:F51) -> 0 | H51: ='Study Data'!E79 -> 0
B52: =B51+1 -> 2049 | F52: ='Study Data'!L80 -> 0 | G52: =SUM(C52:F52) -> 0 | H52: ='Study Data'!E80 -> 0
B53: =B52+1 -> 2050 | F53: ='Study Data'!L81 -> 0 | G53: =SUM(C53:F53) -> 0 | H53: ='Study Data'!E81 -> 0
B54: =B53+1 -> 2051 | F54: ='Study Data'!L82 -> 0 | G54: =SUM(C54:F54) -> 0 | H54: ='Study Data'!E82 -> 0
... B66: =B65+1 -> 2063 | F66: ='Study Data'!L94 -> 0 | G66: =SUM(C66:F66) -> 0 | H66: ='Study Data'!E94 -> 0
B68: Total | C68: =SUM(C27:C67) -> 0 | D68: =SUM(D27:D67) -> 0 | E68: =SUM(E27:E67) -> 0 | F68: =SUM(F27:F67) -> 0 | G68: =SUM(G27:G67) -> 0 | H68: =SUM(H27:H67) -> 0
B71: US Tax Advisors Group, Inc. | 1220 Rosecrans St., Ste 542, San Diego, CA 92106 | (888) 263-1663 | info@ustagi.com

Sheet Real Property
AF8: Repro. Cost New | AG8: Less Depreciation | AH8: Total Cost | AI8: Source
AF9: =IFERROR(AA9*AG9,0) -> 0 | AG9: =IF(AA9=0,"",Calculator!$B$5) | AH9: =(AF9/Calculator!$B$10)*Calculator!$B$9 -> #DIV/0! | AI9: =IF(ISBLANK(AA9),"","RS Means")
AF10: =IFERROR(AA10*AG10,0) -> 0 | AG10: =IF(AA10=0,"",Calculator!$B$5) | AH10: =(AF10/Calculator!$B$10)*Calculator!$B$9 -> #DIV/0! | AI10: =IF(ISBLANK(AA10),"","RS Means")
AF11: =IFERROR(AA11*AG11,0) -> 0 | AG11: =IF(AA11=0,"",Calculator!$B$5) | AH11: =(AF11/Calculator!$B$10)*Calculator!$B$9 -> #DIV/0! | AI11: =IF(ISBLANK(AA11),"","RS Means")
AF12: =IFERROR(AA12*AG12,0) -> 0 | AG12: =IF(AA12=0,"",Calculator!$B$5) | AH12: =(AF12/Calculator!$B$10)*Calculator!$B$9 -> #DIV/0! | AI12: =IF(ISBLANK(AA12),"","RS Means")
AF13: =IFERROR(AA13*AG13,0) -> 0 | AG13: =IF(AA13=0,"",Calculator!$B$5) | AH13: =(AF13/Calculator!$B$10)*Calculator!$B$9 -> #DIV/0! | AI13: =IF(ISBLANK(AA13),"","RS Means")
AF14: =IFERROR(AA14*AG14,0) -> 0 | AG14: =IF(AA14=0,"",Calculator!$B$5) | AH14: =(AF14/Calculator!$B$10)*Calculator!$B$9 -> #DIV/0! | AI14: =IF(ISBLANK(AA14),"","RS Means")
AF15: =IFERROR(AA15*AG15,0) -> 0 | AG15: =IF(AA15=0,"",Calculator!$B$5) | AH15: =(AF15/Calculator!$B$10)*Calculator!$B$9 -> #DIV/0! | AI15: =IF(ISBLANK(AA15),"","RS Means")
AF16: =IFERROR(AA16*AG16,0) -> 0 | AG16: =IF(AA16=0,"",Calculator!$B$5) | AH16: =(AF16/Calculator!$B$10)*Calculator!$B$9 -> #DIV/0! | AI16: =IF(ISBLANK(AA16),"","RS Means")
AF17: =IFERROR(AA17*AG17,0) -> 0 | AG17: =IF(AA17=0,"",Calculator!$B$5) | AH17: =(AF17/Calculator!$B$10)*Calculator!$B$9 -> #DIV/0! | AI17: =IF(ISBLANK(AA17),"","RS Means")
AF18: =IFERROR(AA18*AG18,0) -> 0 | AG18: =IF(AA18=0,"",Calculator!$B$5) | AH18: =(AF18/Calculator!$B$10)*Calculator!$B$9 -> #DIV/0! | AI18: =IF(ISBLANK(AA18),"","RS Means")
AF19: =IFERROR(AA19*AG19,0) -> 0 | AG19: =IF(AA19=0,"",Calculator!$B$5) | AH19: =(AF19/Calculator!$B$10)*Calculator!$B$9 -> #DIV/0! | AI19: =IF(ISBLANK(AA19),"","RS Means")
AF20: =IFERROR(AA20*AG20,0) -> 0 | AG20: =IF(AA20=0,"",Calculator!$B$5) | AH20: =(AF20/Calculator!$B$10)*Calculator!$B$9 -> #DIV/0! | AI20: =IF(ISBLANK(AA20),"","RS Means")
... AF500: =IFERROR(AA500*AG500,0) -> 0 | AG500: =IF(AA500=0,"",Calculator!$B$5) | AH500: =(AF500/Calculator!$B$10)*Calculator!$B$9 -> #DIV/0! | AI500: =IF(ISBLANK(AA500),"","RS Means")

Sheet 15 yr
AF8: Repro. Cost New | AG8: Less Depreciation | AH8: Total Cost | AI8: Source
AF9: =IFERROR(AA9*AG9,0) -> 0 | AG9: =IF(AA9=0,"",Calculator!$B$6) | AH9: =(AF9/Calculator!$B$10)*Calculator!$B$9 -> #DIV/0! | AI9: =IF(ISBLANK(AA9),"","RS Means")
AF10: =IFERROR(AA10*AG10,0) -> 0 | AG10: =IF(AA10=0,"",Calculator!$B$6) | AH10: =(AF10/Calculator!$B$10)*Calculator!$B$9 -> #DIV/0! | AI10: =IF(ISBLANK(AA10),"","RS Means")
AF11: =IFERROR(AA11*AG11,0) -> 0 | AG11: =IF(AA11=0,"",Calculator!$B$6) | AH11: =(AF11/Calculator!$B$10)*Calculator!$B$9 -> #DIV/0! | AI11: =IF(ISBLANK(AA11),"","RS Means")
AF12: =IFERROR(AA12*AG12,0) -> 0 | AG12: =IF(AA12=0,"",Calculator!$B$6) | AH12: =(AF12/Calculator!$B$10)*Calculator!$B$9 -> #DIV/0! | AI12: =IF(ISBLANK(AA12),"","RS Means")
AF13: =IFERROR(AA13*AG13,0) -> 0 | AG13: =IF(AA13=0,"",Calculator!$B$6) | AH13: =(AF13/Calculator!$B$10)*Calculator!$B$9 -> #DIV/0! | AI13: =IF(ISBLANK(AA13),"","RS Means")
AF14: =IFERROR(AA14*AG14,0) -> 0 | AG14: =IF(AA14=0,"",Calculator!$B$6) | AH14: =(AF14/Calculator!$B$10)*Calculator!$B$9 -> #DIV/0! | AI14: =IF(ISBLANK(AA14),"","RS Means")
AF15: =IFERROR(AA15*AG15,0) -> 0 | AG15: =IF(AA15=0,"",Calculator!$B$6) | AH15: =(AF15/Calculator!$B$10)*Calculator!$B$9 -> #DIV/0! | AI15: =IF(ISBLANK(AA15),"","RS Means")
AF16: =IFERROR(AA16*AG16,0) -> 0 | AG16: =IF(AA16=0,"",Calculator!$B$6) | AH16: =(AF16/Calculator!$B$10)*Calculator!$B$9 -> #DIV/0! | AI16: =IF(ISBLANK(AA16),"","RS Means")
AF17: =IFERROR(AA17*AG17,0) -> 0 | AG17: =IF(AA17=0,"",Calculator!$B$6) | AH17: =(AF17/Calculator!$B$10)*Calculator!$B$9 -> #DIV/0! | AI17: =IF(ISBLANK(AA17),"","RS Means")
AF18: =IFERROR(AA18*AG18,0) -> 0 | AG18: =IF(AA18=0,"",Calculator!$B$6) | AH18: =(AF18/Calculator!$B$10)*Calculator!$B$9 -> #DIV/0! | AI18: =IF(ISBLANK(AA18),"","RS Means")
AF19: =IFERROR(AA19*AG19,0) -> 0 | AG19: =IF(AA19=0,"",Calculator!$B$6) | AH19: =(AF19/Calculator!$B$10)*Calculator!$B$9 -> #DIV/0! | AI19: =IF(ISBLANK(AA19),"","RS Means")
AF20: =IFERROR(AA20*AG20,0) -> 0 | AG20: =IF(AA20=0,"",Calculator!$B$6) | AH20: =(AF20/Calculator!$B$10)*Calculator!$B$9 -> #DIV/0! | AI20: =IF(ISBLANK(AA20),"","RS Means")
... AF500: =IFERROR(AA500*AG500,0) -> 0 | AG500: =IF(AA500=0,"",Calculator!$B$6) | AH500: =(AF500/Calculator!$B$10)*Calculator!$B$9 -> #DIV/0! | AI500: =IF(ISBLANK(AA500),"","RS Means")

Sheet 5 yr
AF8: Repro. Cost New | AG8: Less Depreciation | AH8: Total Cost | AI8: Source
AF9: =IFERROR(AA9*AG9,0) -> 0 | AG9: =IF(AA9=0,"",Calculator!$B$7) | AH9: =(AF9/Calculator!$B$10)*Calculator!$B$9 -> #DIV/0! | AI9: =IF(ISBLANK(AA9),"","RS Means")
AF10: =IFERROR(AA10*AG10,0) -> 0 | AG10: =IF(AA10=0,"",Calculator!$B$7) | AH10: =(AF10/Calculator!$B$10)*Calculator!$B$9 -> #DIV/0! | AI10: =IF(ISBLANK(AA10),"","RS Means")
AF11: =IFERROR(AA11*AG11,0) -> 0 | AG11: =IF(AA11=0,"",Calculator!$B$7) | AH11: =(AF11/Calculator!$B$10)*Calculator!$B$9 -> #DIV/0! | AI11: =IF(ISBLANK(AA11),"","RS Means")
AF12: =IFERROR(AA12*AG12,0) -> 0 | AG12: =IF(AA12=0,"",Calculator!$B$7) | AH12: =(AF12/Calculator!$B$10)*Calculator!$B$9 -> #DIV/0! | AI12: =IF(ISBLANK(AA12),"","RS Means")
AF13: =IFERROR(AA13*AG13,0) -> 0 | AG13: =IF(AA13=0,"",Calculator!$B$7) | AH13: =(AF13/Calculator!$B$10)*Calculator!$B$9 -> #DIV/0! | AI13: =IF(ISBLANK(AA13),"","RS Means")
AF14: =IFERROR(AA14*AG14,0) -> 0 | AG14: =IF(AA14=0,"",Calculator!$B$7) | AH14: =(AF14/Calculator!$B$10)*Calculator!$B$9 -> #DIV/0! | AI14: =IF(ISBLANK(AA14),"","RS Means")
AF15: =IFERROR(AA15*AG15,0) -> 0 | AG15: =IF(AA15=0,"",Calculator!$B$7) | AH15: =(AF15/Calculator!$B$10)*Calculator!$B$9 -> #DIV/0! | AI15: =IF(ISBLANK(AA15),"","RS Means")
AF16: =IFERROR(AA16*AG16,0) -> 0 | AG16: =IF(AA16=0,"",Calculator!$B$7) | AH16: =(AF16/Calculator!$B$10)*Calculator!$B$9 -> #DIV/0! | AI16: =IF(ISBLANK(AA16),"","RS Means")
AF17: =IFERROR(AA17*AG17,0) -> 0 | AG17: =IF(AA17=0,"",Calculator!$B$7) | AH17: =(AF17/Calculator!$B$10)*Calculator!$B$9 -> #DIV/0! | AI17: =IF(ISBLANK(AA17),"","RS Means")
AF18: =IFERROR(AA18*AG18,0) -> 0 | AG18: =IF(AA18=0,"",Calculator!$B$7) | AH18: =(AF18/Calculator!$B$10)*Calculator!$B$9 -> #DIV/0! | AI18: =IF(ISBLANK(AA18),"","RS Means")
AF19: =IFERROR(AA19*AG19,0) -> 0 | AG19: =IF(AA19=0,"",Calculator!$B$7) | AH19: =(AF19/Calculator!$B$10)*Calculator!$B$9 -> #DIV/0! | AI19: =IF(ISBLANK(AA19),"","RS Means")
AF20: =IFERROR(AA20*AG20,0) -> 0 | AG20: =IF(AA20=0,"",Calculator!$B$7) | AH20: =(AF20/Calculator!$B$10)*Calculator!$B$9 -> #DIV/0! | AI20: =IF(ISBLANK(AA20),"","RS Means")
... AF500: =IFERROR(AA500*AG500,0) -> 0 | AG500: =IF(AA500=0,"",Calculator!$B$7) | AH500: =(AF500/Calculator!$B$10)*Calculator!$B$9 -> #DIV/0! | AI500: =IF(ISBLANK(AA500),"","RS Means")

Sheet Calculator
A1: In-Service Date | B1: ='Client Summary'!G13 -> 45292
A2: Address | B2: ='Client Summary'!G12 -> 861 E 800 S, Salt Lake City, UT 84102
A4: Rec Period | B4: RCN # | C4: Accelerated # | D4: Yield
A5: ='Client Summary'!$G$26&" year" -> 27.5 year | B5: 1 | C5: =_xlfn.IFNA((INDEX('Real Property'!$AF:$AF,MATCH("Grand Total",'Real Property'!$A:$A,0))/$B$10)*$B$9,0) -> 0 | D5: =IFERROR((C5/B9)*1,0) -> 0
A6: 15 year | B6: 1 | C6: =_xlfn.IFNA((INDEX('15 yr'!$AF:$AF,MATCH("Grand Total",'15 yr'!$A:$A,0))/$B$10)*$B$9,0) -> 0 | D6: =IFERROR((C6/B9)*1,0) -> 0
A7: 5 year | B7: 1 | C7: =_xlfn.IFNA((INDEX('5 yr'!$AF:$AF,MATCH("Grand Total",'5 yr'!$A:$A,0))/$B$10)*$B$9,0) -> 0 | D7: =IFERROR((C7/B9)*1,0) -> 0
A8: RCN | B8: =SUM(B5:B7) -> 3 | C8: =SUM(C6:C7) -> 0 | D8: =SUM(D6:D7) -> 0
A9: BASIS | B9: ='Client Summary'!G18 -> 0
A10: RCN | B10: =_xlfn.IFNA(INDEX('Real Property'!$AF:$AF,MATCH("Grand Total",'Real Property'!$A:$A,0))+INDEX('15 yr'!$AF:$AF,MATCH("Grand Total",'15 yr'!$A:$A,0))+INDEX('5 yr'!$AF:$AF,MATCH("Grand Total",'5 yr'!$A:$A,0)),0) -> 0

Sheet Recovery Period Summary
A1: #VALUE!
E11: Recovery Period Summary
D13: Property Address: | E13: =LEFT('Client Summary'!G12,FIND(",",'Client Summary'!G12)-1) -> 861 E 800 S
D14: Depreciation Method: | E14: ='Client Summary'!G20 -> Residential
D15: Building Use: | E15: =_xlfn.XLOOKUP('Client Summary'!$G$21,Definitions!$E$2:$E$35,Definitions!$F$2:$F$35,0,0,1) -> Single Family Residence
D16: Date Placed in Service: | E16: ='Client Summary'!G13 -> 45292
D17: Cost Basis: | E17: ='Client Summary'!G14 -> 0
D18: Land Allocation: | E18: ='Client Summary'!G15 -> 0
D19: Building Basis: | E19: ='Client Summary'!G16 -> 0
D20: Improvements included in the Study: | E20: ='Client Summary'!G17 -> 0
D21: Basis for Cost Segregation: | E21: ='Client Summary'!G18 -> 0
D22: ="Accumulated Depreciation as of 12/31/"&'Study Data'!$B$5-1&":" -> Accumulated Depreciation as of 12/31/2024: | E22: ='Client Summary'!G19 -> 0
B25: Recovery Period - Property Type | C25: MACRS | D25: Total Cost | E25: Dep Method
B27: 5 Years: 1245 Property - Distributive Trades & Services | C27: 57 | D27: =_xlfn.IFNA(INDEX('5 Years'!A:I,MATCH("Grand Total",'5 Years'!A:A,0),6),0) -> 0 | E27: 200% DB
B28: 15 Years: 1245 & 1250 Property - Land Improvements | C28: 0.3 | D28: =_xlfn.IFNA(INDEX('15 Years'!A:I,MATCH("Grand Total",'15 Years'!A:A,0),6),0) -> 0 | E28: 150% DB
B29: 27.5 Years: 1250 Real Property | D29: =_xlfn.IFNA(INDEX('Real Property Final'!A:I,MATCH("Grand Total",'Real Property Final'!A:A,0),6),0) -> 0 | E29: SL
B31: Total Depreciable Basis | D31: =SUM(D27:D29) -> 0

Sheet Real Property Final
A1: ='Client Summary'!G26&" Years Property Summary" -> 27.5 Years Property Summary
A2: =LEFT('Client Summary'!G12,FIND(",",'Client Summary'!G12)-1) -> 861 E 800 S
A4: Unit Cost Lines
A5: Quantity | B5: LineNumber | C5: Description | D5: Unit | E5: RCN | F5: Total Cost | G5: Cost Source
A6: =IF('Real Property'!A9=0,"",'Real Property'!A9) | B6: =IF('Real Property'!B9=0,"",'Real Property'!B9) | C6: =IF('Real Property'!E9=0,"",'Real Property'!E9) | D6: =IF('Real Property'!I9=0,"",'Real Property'!I9) | E6: =IFERROR(IF('Real Property'!AF9=0,"",'Real Property'!AF9),"") | F6: =IFERROR(IF('Real Property'!AH9=0,"",'Real Property'!AH9),"") | G6: =IF('Real Property'!AI9=0,"",'Real Property'!AI9)
A7: =IF('Real Property'!A10=0,"",'Real Property'!A10) | B7: =IF('Real Property'!B10=0,"",'Real Property'!B10) | C7: =IF('Real Property'!E10=0,"",'Real Property'!E10) | D7: =IF('Real Property'!I10=0,"",'Real Property'!I10) | E7: =IFERROR(IF('Real Property'!AF10=0,"",'Real Property'!AF10),"") | F7: =IFERROR(IF('Real Property'!AH10=0,"",'Real Property'!AH10),"") | G7: =IF('Real Property'!AI10=0,"",'Real Property'!AI10)
A8: =IF('Real Property'!A11=0,"",'Real Property'!A11) | B8: =IF('Real Property'!B11=0,"",'Real Property'!B11) | C8: =IF('Real Property'!E11=0,"",'Real Property'!E11) | D8: =IF('Real Property'!I11=0,"",'Real Property'!I11) | E8: =IFERROR(IF('Real Property'!AF11=0,"",'Real Property'!AF11),"") | F8: =IFERROR(IF('Real Property'!AH11=0,"",'Real Property'!AH11),"") | G8: =IF('Real Property'!AI11=0,"",'Real Property'!AI11)
A9: =IF('Real Property'!A12=0,"",'Real Property'!A12) | B9: =IF('Real Property'!B12=0,"",'Real Property'!B12) | C9: =IF('Real Property'!E12=0,"",'Real Property'!E12) | D9: =IF('Real Property'!I12=0,"",'Real Property'!I12) | E9: =IFERROR(IF('Real Property'!AF12=0,"",'Real Property'!AF12),"") | F9: =IFERROR(IF('Real Property'!AH12=0,"",'Real Property'!AH12),"") | G9: =IF('Real Property'!AI12=0,"",'Real Property'!AI12)
A10: =IF('Real Property'!A13=0,"",'Real Property'!A13) | B10: =IF('Real Property'!B13=0,"",'Real Property'!B13) | C10: =IF('Real Property'!E13=0,"",'Real Property'!E13) | D10: =IF('Real Property'!I13=0,"",'Real Property'!I13) | E10: =IFERROR(IF('Real Property'!AF13=0,"",'Real Property'!AF13),"") | F10: =IFERROR(IF('Real Property'!AH13=0,"",'Real Property'!AH13),"") | G10: =IF('Real Property'!AI13=0,"",'Real Property'!AI13)
A11: =IF('Real Property'!A14=0,"",'Real Property'!A14) | B11: =IF('Real Property'!B14=0,"",'Real Property'!B14) | C11: =IF('Real Property'!E14=0,"",'Real Property'!E14) | D11: =IF('Real Property'!I14=0,"",'Real Property'!I14) | E11: =IFERROR(IF('Real Property'!AF14=0,"",'Real Property'!AF14),"") | F11: =IFERROR(IF('Real Property'!AH14=0,"",'Real Property'!AH14),"") | G11: =IF('Real Property'!AI14=0,"",'Real Property'!AI14)
A12: =IF('Real Property'!A15=0,"",'Real Property'!A15) | B12: =IF('Real Property'!B15=0,"",'Real Property'!B15) | C12: =IF('Real Property'!E15=0,"",'Real Property'!E15) | D12: =IF('Real Property'!I15=0,"",'Real Property'!I15) | E12: =IFERROR(IF('Real Property'!AF15=0,"",'Real Property'!AF15),"") | F12: =IFERROR(IF('Real Property'!AH15=0,"",'Real Property'!AH15),"") | G12: =IF('Real Property'!AI15=0,"",'Real Property'!AI15)
A13: =IF('Real Property'!A16=0,"",'Real Property'!A16) | B13: =IF('Real Property'!B16=0,"",'Real Property'!B16) | C13: =IF('Real Property'!E16=0,"",'Real Property'!E16) | D13: =IF('Real Property'!I16=0,"",'Real Property'!I16) | E13: =IFERROR(IF('Real Property'!AF16=0,"",'Real Property'!AF16),"") | F13: =IFERROR(IF('Real Property'!AH16=0,"",'Real Property'!AH16),"") | G13: =IF('Real Property'!AI16=0,"",'Real Property'!AI16)
A14: =IF('Real Property'!A17=0,"",'Real Property'!A17) | B14: =IF('Real Property'!B17=0,"",'Real Property'!B17) | C14: =IF('Real Property'!E17=0,"",'Real Property'!E17) | D14: =IF('Real Property'!I17=0,"",'Real Property'!I17) | E14: =IFERROR(IF('Real Property'!AF17=0,"",'Real Property'!AF17),"") | F14: =IFERROR(IF('Real Property'!AH17=0,"",'Real Property'!AH17),"") | G14: =IF('Real Property'!AI17=0,"",'Real Property'!AI17)
A15: =IF('Real Property'!A18=0,"",'Real Property'!A18) | B15: =IF('Real Property'!B18=0,"",'Real Property'!B18) | C15: =IF('Real Property'!E18=0,"",'Real Property'!E18) | D15: =IF('Real Property'!I18=0,"",'Real Property'!I18) | E15: =IFERROR(IF('Real Property'!AF18=0,"",'Real Property'!AF18),"") | F15: =IFERROR(IF('Real Property'!AH18=0,"",'Real Property'!AH18),"") | G15: =IF('Real Property'!AI18=0,"",'Real Property'!AI18)
A16: =IF('Real Property'!A19=0,"",'Real Property'!A19) | B16: =IF('Real Property'!B19=0,"",'Real Property'!B19) | C16: =IF('Real Property'!E19=0,"",'Real Property'!E19) | D16: =IF('Real Property'!I19=0,"",'Real Property'!I19) | E16: =IFERROR(IF('Real Property'!AF19=0,"",'Real Property'!AF19),"") | F16: =IFERROR(IF('Real Property'!AH19=0,"",'Real Property'!AH19),"") | G16: =IF('Real Property'!AI19=0,"",'Real Property'!AI19)
A17: =IF('Real Property'!A20=0,"",'Real Property'!A20) | B17: =IF('Real Property'!B20=0,"",'Real Property'!B20) | C17: =IF('Real Property'!E20=0,"",'Real Property'!E20) | D17: =IF('Real Property'!I20=0,"",'Real Property'!I20) | E17: =IFERROR(IF('Real Property'!AF20=0,"",'Real Property'!AF20),"") | F17: =IFERROR(IF('Real Property'!AH20=0,"",'Real Property'!AH20),"") | G17: =IF('Real Property'!AI20=0,"",'Real Property'!AI20)
... A500: =IF('Real Property'!A503=0,"",'Real Property'!A503) | B500: =IF('Real Property'!B503=0,"",'Real Property'!B503) | C500: =IF('Real Property'!E503=0,"",'Real Property'!E503) | D500: =IF('Real Property'!I503=0,"",'Real Property'!I503) | E500: =IFERROR(IF('Real Property'!AF503=0,"",'Real Property'!AF503),"") | F500: =IFERROR(IF('Real Property'!AH503=0,"",'Real Property'!AH503),"") | G500: =IF('Real Property'!AI503=0,"",'Real Property'!AI503)

Sheet 15 Years
A1: ='Client Summary'!G29&" Years Property Summary" -> 15 Years Property Summary
A2: =LEFT('Client Summary'!G12,FIND(",",'Client Summary'!G12)-1) -> 861 E 800 S
A4: Unit Cost Lines
A5: Quantity | B5: LineNumber | C5: Description | D5: Unit | E5: RCN | F5: Total Cost | G5: Cost Source
A6: =IF('15 yr'!A9=0,"",'15 yr'!A9) | B6: =IF('15 yr'!B9=0,"",'15 yr'!B9) | C6: =IF('15 yr'!E9=0,"",'15 yr'!E9) | D6: =IF('15 yr'!I9=0,"",'15 yr'!I9) | E6: =IFERROR(IF('15 yr'!AF9=0,"",'15 yr'!AF9),"") | F6: =IFERROR(IF('15 yr'!AH9=0,"",'15 yr'!AH9),"") | G6: =IFERROR(IF('15 yr'!AI9=0,"",'15 yr'!AI9),"")
A7: =IF('15 yr'!A10=0,"",'15 yr'!A10) | B7: =IF('15 yr'!B10=0,"",'15 yr'!B10) | C7: =IF('15 yr'!E10=0,"",'15 yr'!E10) | D7: =IF('15 yr'!I10=0,"",'15 yr'!I10) | E7: =IFERROR(IF('15 yr'!AF10=0,"",'15 yr'!AF10),"") | F7: =IFERROR(IF('15 yr'!AH10=0,"",'15 yr'!AH10),"") | G7: =IFERROR(IF('15 yr'!AI10=0,"",'15 yr'!AI10),"")
A8: =IF('15 yr'!A11=0,"",'15 yr'!A11) | B8: =IF('15 yr'!B11=0,"",'15 yr'!B11) | C8: =IF('15 yr'!E11=0,"",'15 yr'!E11) | D8: =IF('15 yr'!I11=0,"",'15 yr'!I11) | E8: =IFERROR(IF('15 yr'!AF11=0,"",'15 yr'!AF11),"") | F8: =IFERROR(IF('15 yr'!AH11=0,"",'15 yr'!AH11),"") | G8: =IFERROR(IF('15 yr'!AI11=0,"",'15 yr'!AI11),"")
A9: =IF('15 yr'!A12=0,"",'15 yr'!A12) | B9: =IF('15 yr'!B12=0,"",'15 yr'!B12) | C9: =IF('15 yr'!E12=0,"",'15 yr'!E12) | D9: =IF('15 yr'!I12=0,"",'15 yr'!I12) | E9: =IFERROR(IF('15 yr'!AF12=0,"",'15 yr'!AF12),"") | F9: =IFERROR(IF('15 yr'!AH12=0,"",'15 yr'!AH12),"") | G9: =IFERROR(IF('15 yr'!AI12=0,"",'15 yr'!AI12),"")
A10: =IF('15 yr'!A13=0,"",'15 yr'!A13) | B10: =IF('15 yr'!B13=0,"",'15 yr'!B13) | C10: =IF('15 yr'!E13=0,"",'15 yr'!E13) | D10: =IF('15 yr'!I13=0,"",'15 yr'!I13) | E10: =IFERROR(IF('15 yr'!AF13=0,"",'15 yr'!AF13),"") | F10: =IFERROR(IF('15 yr'!AH13=0,"",'15 yr'!AH13),"") | G10: =IFERROR(IF('15 yr'!AI13=0,"",'15 yr'!AI13),"")
A11: =IF('15 yr'!A14=0,"",'15 yr'!A14) | B11: =IF('15 yr'!B14=0,"",'15 yr'!B14) | C11: =IF('15 yr'!E14=0,"",'15 yr'!E14) | D11: =IF('15 yr'!I14=0,"",'15 yr'!I14) | E11: =IFERROR(IF('15 yr'!AF14=0,"",'15 yr'!AF14),"") | F11: =IFERROR(IF('15 yr'!AH14=0,"",'15 yr'!AH14),"") | G11: =IFERROR(IF('15 yr'!AI14=0,"",'15 yr'!AI14),"")
A12: =IF('15 yr'!A15=0,"",'15 yr'!A15) | B12: =IF('15 yr'!B15=0,"",'15 yr'!B15) | C12: =IF('15 yr'!E15=0,"",'15 yr'!E15) | D12: =IF('15 yr'!I15=0,"",'15 yr'!I15) | E12: =IFERROR(IF('15 yr'!AF15=0,"",'15 yr'!AF15),"") | F12: =IFERROR(IF('15 yr'!AH15=0,"",'15 yr'!AH15),"") | G12: =IFERROR(IF('15 yr'!AI15=0,"",'15 yr'!AI15),"")
A13: =IF('15 yr'!A16=0,"",'15 yr'!A16) | B13: =IF('15 yr'!B16=0,"",'15 yr'!B16) | C13: =IF('15 yr'!E16=0,"",'15 yr'!E16) | D13: =IF('15 yr'!I16=0,"",'15 yr'!I16) | E13: =IFERROR(IF('15 yr'!AF16=0,"",'15 yr'!AF16),"") | F13: =IFERROR(IF('15 yr'!AH16=0,"",'15 yr'!AH16),"") | G13: =IFERROR(IF('15 yr'!AI16=0,"",'15 yr'!AI16),"")
A14: =IF('15 yr'!A17=0,"",'15 yr'!A17) | B14: =IF('15 yr'!B17=0,"",'15 yr'!B17) | C14: =IF('15 yr'!E17=0,"",'15 yr'!E17) | D14: =IF('15 yr'!I17=0,"",'15 yr'!I17) | E14: =IFERROR(IF('15 yr'!AF17=0,"",'15 yr'!AF17),"") | F14: =IFERROR(IF('15 yr'!AH17=0,"",'15 yr'!AH17),"") | G14: =IFERROR(IF('15 yr'!AI17=0,"",'15 yr'!AI17),"")
A15: =IF('15 yr'!A18=0,"",'15 yr'!A18) | B15: =IF('15 yr'!B18=0,"",'15 yr'!B18) | C15: =IF('15 yr'!E18=0,"",'15 yr'!E18) | D15: =IF('15 yr'!I18=0,"",'15 yr'!I18) | E15: =IFERROR(IF('15 yr'!AF18=0,"",'15 yr'!AF18),"") | F15: =IFERROR(IF('15 yr'!AH18=0,"",'15 yr'!AH18),"") | G15: =IFERROR(IF('15 yr'!AI18=0,"",'15 yr'!AI18),"")
A16: =IF('15 yr'!A19=0,"",'15 yr'!A19) | B16: =IF('15 yr'!B19=0,"",'15 yr'!B19) | C16: =IF('15 yr'!E19=0,"",'15 yr'!E19) | D16: =IF('15 yr'!I19=0,"",'15 yr'!I19) | E16: =IFERROR(IF('15 yr'!AF19=0,"",'15 yr'!AF19),"") | F16: =IFERROR(IF('15 yr'!AH19=0,"",'15 yr'!AH19),"") | G16: =IFERROR(IF('15 yr'!AI19=0,"",'15 yr'!AI19),"")
A17: =IF('15 yr'!A20=0,"",'15 yr'!A20) | B17: =IF('15 yr'!B20=0,"",'15 yr'!B20) | C17: =IF('15 yr'!E20=0,"",'15 yr'!E20) | D17: =IF('15 yr'!I20=0,"",'15 yr'!I20) | E17: =IFERROR(IF('15 yr'!AF20=0,"",'15 yr'!AF20),"") | F17: =IFERROR(IF('15 yr'!AH20=0,"",'15 yr'!AH20),"") | G17: =IFERROR(IF('15 yr'!AI20=0,"",'15 yr'!AI20),"")
... A500: =IF('15 yr'!A503=0,"",'15 yr'!A503) | B500: =IF('15 yr'!B503=0,"",'15 yr'!B503) | C500: =IF('15 yr'!E503=0,"",'15 yr'!E503) | D500: =IF('15 yr'!I503=0,"",'15 yr'!I503) | E500: =IFERROR(IF('15 yr'!AF503=0,"",'15 yr'!AF503),"") | F500: =IFERROR(IF('15 yr'!AH503=0,"",'15 yr'!AH503),"") | G500: =IFERROR(IF('15 yr'!AI503=0,"",'15 yr'!AI503),"")

Sheet 5 Years
A1: ='Client Summary'!G27&" Years Property Summary" -> 5 Years Property Summary
A2: =LEFT('Client Summary'!G12,FIND(",",'Client Summary'!G12)-1) -> 861 E 800 S
A4: Unit Cost Lines
A5: Quantity | B5: LineNumber | C5: Description | D5: Unit | E5: RCN | F5: Total Cost | G5: Cost Source
A6: =IF('5 yr'!A9=0,"",'5 yr'!A9) | B6: =IF('5 yr'!B9=0,"",'5 yr'!B9) | C6: =IF('5 yr'!E9=0,"",'5 yr'!E9) | D6: =IF('5 yr'!I9=0,"",'5 yr'!I9) | E6: =IFERROR(IF('5 yr'!AF9=0,"",'5 yr'!AF9),"") | F6: =IFERROR(IF('5 yr'!AH9=0,"",'5 yr'!AH9),"") | G6: =IFERROR(IF('5 yr'!AI9=0,"",'5 yr'!AI9),"")
A7: =IF('5 yr'!A10=0,"",'5 yr'!A10) | B7: =IF('5 yr'!B10=0,"",'5 yr'!B10) | C7: =IF('5 yr'!E10=0,"",'5 yr'!E10) | D7: =IF('5 yr'!I10=0,"",'5 yr'!I10) | E7: =IFERROR(IF('5 yr'!AF10=0,"",'5 yr'!AF10),"") | F7: =IFERROR(IF('5 yr'!AH10=0,"",'5 yr'!AH10),"") | G7: =IFERROR(IF('5 yr'!AI10=0,"",'5 yr'!AI10),"")
A8: =IF('5 yr'!A11=0,"",'5 yr'!A11) | B8: =IF('5 yr'!B11=0,"",'5 yr'!B11) | C8: =IF('5 yr'!E11=0,"",'5 yr'!E11) | D8: =IF('5 yr'!I11=0,"",'5 yr'!I11) | E8: =IFERROR(IF('5 yr'!AF11=0,"",'5 yr'!AF11),"") | F8: =IFERROR(IF('5 yr'!AH11=0,"",'5 yr'!AH11),"") | G8: =IFERROR(IF('5 yr'!AI11=0,"",'5 yr'!AI11),"")
A9: =IF('5 yr'!A12=0,"",'5 yr'!A12) | B9: =IF('5 yr'!B12=0,"",'5 yr'!B12) | C9: =IF('5 yr'!E12=0,"",'5 yr'!E12) | D9: =IF('5 yr'!I12=0,"",'5 yr'!I12) | E9: =IFERROR(IF('5 yr'!AF12=0,"",'5 yr'!AF12),"") | F9: =IFERROR(IF('5 yr'!AH12=0,"",'5 yr'!AH12),"") | G9: =IFERROR(IF('5 yr'!AI12=0,"",'5 yr'!AI12),"")
A10: =IF('5 yr'!A13=0,"",'5 yr'!A13) | B10: =IF('5 yr'!B13=0,"",'5 yr'!B13) | C10: =IF('5 yr'!E13=0,"",'5 yr'!E13) | D10: =IF('5 yr'!I13=0,"",'5 yr'!I13) | E10: =IFERROR(IF('5 yr'!AF13=0,"",'5 yr'!AF13),"") | F10: =IFERROR(IF('5 yr'!AH13=0,"",'5 yr'!AH13),"") | G10: =IFERROR(IF('5 yr'!AI13=0,"",'5 yr'!AI13),"")
A11: =IF('5 yr'!A14=0,"",'5 yr'!A14) | B11: =IF('5 yr'!B14=0,"",'5 yr'!B14) | C11: =IF('5 yr'!E14=0,"",'5 yr'!E14) | D11: =IF('5 yr'!I14=0,"",'5 yr'!I14) | E11: =IFERROR(IF('5 yr'!AF14=0,"",'5 yr'!AF14),"") | F11: =IFERROR(IF('5 yr'!AH14=0,"",'5 yr'!AH14),"") | G11: =IFERROR(IF('5 yr'!AI14=0,"",'5 yr'!AI14),"")
A12: =IF('5 yr'!A15=0,"",'5 yr'!A15) | B12: =IF('5 yr'!B15=0,"",'5 yr'!B15) | C12: =IF('5 yr'!E15=0,"",'5 yr'!E15) | D12: =IF('5 yr'!I15=0,"",'5 yr'!I15) | E12: =IFERROR(IF('5 yr'!AF15=0,"",'5 yr'!AF15),"") | F12: =IFERROR(IF('5 yr'!AH15=0,"",'5 yr'!AH15),"") | G12: =IFERROR(IF('5 yr'!AI15=0,"",'5 yr'!AI15),"")
A13: =IF('5 yr'!A16=0,"",'5 yr'!A16) | B13: =IF('5 yr'!B16=0,"",'5 yr'!B16) | C13: =IF('5 yr'!E16=0,"",'5 yr'!E16) | D13: =IF('5 yr'!I16=0,"",'5 yr'!I16) | E13: =IFERROR(IF('5 yr'!AF16=0,"",'5 yr'!AF16),"") | F13: =IFERROR(IF('5 yr'!AH16=0,"",'5 yr'!AH16),"") | G13: =IFERROR(IF('5 yr'!AI16=0,"",'5 yr'!AI16),"")
A14: =IF('5 yr'!A17=0,"",'5 yr'!A17) | B14: =IF('5 yr'!B17=0,"",'5 yr'!B17) | C14: =IF('5 yr'!E17=0,"",'5 yr'!E17) | D14: =IF('5 yr'!I17=0,"",'5 yr'!I17) | E14: =IFERROR(IF('5 yr'!AF17=0,"",'5 yr'!AF17),"") | F14: =IFERROR(IF('5 yr'!AH17=0,"",'5 yr'!AH17),"") | G14: =IFERROR(IF('5 yr'!AI17=0,"",'5 yr'!AI17),"")
A15: =IF('5 yr'!A18=0,"",'5 yr'!A18) | B15: =IF('5 yr'!B18=0,"",'5 yr'!B18) | C15: =IF('5 yr'!E18=0,"",'5 yr'!E18) | D15: =IF('5 yr'!I18=0,"",'5 yr'!I18) | E15: =IFERROR(IF('5 yr'!AF18=0,"",'5 yr'!AF18),"") | F15: =IFERROR(IF('5 yr'!AH18=0,"",'5 yr'!AH18),"") | G15: =IFERROR(IF('5 yr'!AI18=0,"",'5 yr'!AI18),"")
A16: =IF('5 yr'!A19=0,"",'5 yr'!A19) | B16: =IF('5 yr'!B19=0,"",'5 yr'!B19) | C16: =IF('5 yr'!E19=0,"",'5 yr'!E19) | D16: =IF('5 yr'!I19=0,"",'5 yr'!I19) | E16: =IFERROR(IF('5 yr'!AF19=0,"",'5 yr'!AF19),"") | F16: =IFERROR(IF('5 yr'!AH19=0,"",'5 yr'!AH19),"") | G16: =IFERROR(IF('5 yr'!AI19=0,"",'5 yr'!AI19),"")
A17: =IF('5 yr'!A20=0,"",'5 yr'!A20) | B17: =IF('5 yr'!B20=0,"",'5 yr'!B20) | C17: =IF('5 yr'!E20=0,"",'5 yr'!E20) | D17: =IF('5 yr'!I20=0,"",'5 yr'!I20) | E17: =IFERROR(IF('5 yr'!AF20=0,"",'5 yr'!AF20),"") | F17: =IFERROR(IF('5 yr'!AH20=0,"",'5 yr'!AH20),"") | G17: =IFERROR(IF('5 yr'!AI20=0,"",'5 yr'!AI20),"")
... A500: =IF('5 yr'!A503=0,"",'5 yr'!A503) | B500: =IF('5 yr'!B503=0,"",'5 yr'!B503) | C500: =IF('5 yr'!E503=0,"",'5 yr'!E503) | D500: =IF('5 yr'!I503=0,"",'5 yr'!I503) | E500: =IFERROR(IF('5 yr'!AF503=0,"",'5 yr'!AF503),"") | F500: =IFERROR(IF('5 yr'!AH503=0,"",'5 yr'!AH503),"") | G500: =IFERROR(IF('5 yr'!AI503=0,"",'5 yr'!AI503),"")

Sheet Estimator
A1: Property Type | B1: Guideline | C1: Dep. Life | D1: Total Accelerated | E1: 39-yr or 27.5-yr | F1: 15-yr | G1: 7-yr | H1: 5-yr
A3: Assisted Living | B3: 57 | C3: 5 | D3: 0.24 | E3: 0.76 | F3: 0.09 | G3: 0 | H3: 0.15
A4: Auction Facility | B4: None | C4: 7 | D4: 0.3 | E4: 0.7 | F4: 0.18 | G4: 0.12 | H4: 0
A5: Bank | B5: 57 | C5: 5 | D5: 0.27 | E5: 0.73 | F5: 0.12 | G5: 0 | H5: 0.15
A6: Car Dealer | B6: 57 | C6: 5 | D6: 0.22 | E6: 0.78 | F6: 0.12 | G6: 0 | H6: 0.1
A7: Car Wash | B7: 57 | C7: 5 | D7: 1 | E7: 0 | F7: 0.95 | G7: 0 | H7: 0.05
A8: Car-Truck Repair | B8: 57 | C8: 5 | D8: 0.25 | E8: 0.75 | F8: 0.1 | G8: 0 | H8: 0.15
A9: Casino | B9: 79 | C9: 7 | D9: 0.35 | E9: 0.65 | F9: 0.1 | G9: 0.25 | H9: 0
A10: Cinemas | B10: 79 | C10: 7 | D10: 0.22 | E10: 0.78 | F10: 0.1 | G10: 0.12 | H10: 0
A11: Data Center | B11: 57 | C11: 5 | D11: 0.4 | E11: 0.6 | F11: 0.15 | G11: 0 | H11: 0.25
A12: Daycare Facility | B12: 57 | C12: 5 | D12: 0.2 | E12: 0.8 | F12: 0.1 | G12: 0 | H12: 0.1
A13: Distribution Facility | B13: 57 | C13: 5 | D13: 0.2 | E13: 0.8 | F13: 0.12 | G13: 0 | H13: 0.08
A14: Drug Store | B14: 57 | C14: 5 | D14: 0.3 | E14: 0.7 | F14: 0.18 | G14: 0 | H14: 0.12
A15: Fitness Center | B15: 57 | C15: 5 | D15: 0.25 | E15: 0.75 | F15: 0.05 | G15: 0 | H15: 0.2
A16: Funeral Home | B16: 57 | C16: 5 | D16: 0.25 | E16: 0.75 | F16: 0.1 | G16: 0 | H16: 0.15
... A67: Office Park | B67: 57 | C67: 5 | D67: 0.18 | E67: 0.82 | F67: 0.1 | G67: 0 | H67: 0.08
A68: Parking Structure | B68: None | C68: 39 | D68: 0.05 | E68: 0.95 | F68: 0 | G68: 0 | H68: 0.05
A69: Pharmaceutical Plant | B69: 28 | C69: 5 | D69: 0.34 | E69: 0.66 | F69: 0.1 | G69: 0 | H69: 0.24
A70: Printing, Publishing & Allied Industries | B70: 27 | C70: 7 | D70: 0.45 | E70: 0.55 | F70: 0.1 | G70: 0.35 | H70: 0
A71: R&D Facility | B71: 36 | C71: 5 | D71: 0.34 | E71: 0.66 | F71: 0.1 | G71: 0 | H71: 0.24
A72: Recreation | B72: 79 | C72: 7 | D72: 0.28 | E72: 0.72 | F72: 0.12 | G72: 0.16 | H72: 0
A73: Resort | B73: 57 | C73: 5 | D73: 0.3 | E73: 0.7 | F73: 0.15 | G73: 0 | H73: 0.15
A74: Restaurant - Franchise | B74: 57 | C74: 5 | D74: 0.25 | E74: 0.75 | F74: 0.1 | G74: 0 | H74: 0.15
A75: Restaurant - High End | B75: 57 | C75: 5 | D75: 0.35 | E75: 0.65 | F75: 0.12 | G75: 0 | H75: 0.23
A76: Restaurant - Quick Service | B76: 57 | C76: 5 | D76: 0.3 | E76: 0.7 | F76: 0.15 | G76: 0 | H76: 0.15
A77: Restaurant - With Lease | B77: 57 | C77: 5 | D77: 0.25 | E77: 0.75 | F77: 0.1 | G77: 0 | H77: 0.15
A78: Retail - Big Box | B78: 57 | C78: 5 | D78: 0.32 | E78: 0.68 | F78: 0.2 | G78: 0 | H78: 0.12
A79: Retail Store | B79: 57 | C79: 5 | D79: 0.15 | E79: 0.85 | F79: 0.1 | G79: 0 | H79: 0.05
A80: School, for profit | B80: None | C80: 7 | D80: 0.3 | E80: 0.7 | F80: 0.12 | G80: 0.18 | H80: 0
A81: School, non-profit | B81: None | C81: 12 | D81: 0.3 | E81: 0.7 | F81: 0.12 | G81: 0.18 | H81: 0
A82: Self Storage Facility | B82: 57 | C82: 5 | D82: 0.3 | E82: 0.7 | F82: 0.15 | G82: 0 | H82: 0.15
A83: Shopping Center with TI | B83: 57 | C83: 5 | D83: 0.25 | E83: 0.75 | F83: 0.15 | G83: 0 | H83: 0.1
A84: Shopping Center w/o TI | B84: 57 | C84: 5 | D84: 0.18 | E84: 0.82 | F84: 0.15 | G84: 0 | H84: 0.03
A85: Shopping Center w/o TI, Supermarket Anchor | B85: 57 | C85: 5 | D85: 0.3 | E85: 0.7 | F85: 0.2 | G85: 0 | H85: 0.1
A86: Truck Stop | B86: 57.1 | C86: 5 | D86: 1 | E86: 0 | F86: 0.6 | G86: 0 | H86: 0.4
A87: Veterinary Clinic | B87: 57 | C87: 5 | D87: 0.25 | E87: 0.75 | F87: 0.1 | G87: 0 | H87: 0.15
A88: Warehouse Facility | B88: 57 | C88: 5 | D88: 0.14 | E88: 0.86 | F88: 0.12 | G88: 0 | H88: 0.02
A89: Warehouse Facility, Manufacturing | B89: None | C89: 7 | D89: 0.15 | E89: 0.85 | F89: 0.1 | G89: 0.05 | H89: 0

Sheet 27.5-Year
A1: 27.5-Year Asset | B1: SL | O1: Mid-Month Convention
A2: Month In Service | B2: January | C2: February | D2: March | E2: April | F2: May | G2: June | H2: July | I2: August | J2: September | K2: October | L2: November | M2: December | O2: Residential Rental Property
A3: Year No. | B3: 1 | C3: 2 | D3: 3 | E3: 4 | F3: 5 | G3: 6 | H3: 7 | I3: 8 | J3: 9 | K3: 10 | L3: 11 | M3: 12
A4: 1 | B4: 0.03485 | C4: 0.03182 | D4: 0.02879 | E4: 0.02576 | F4: 0.02273 | G4: 0.0197 | H4: 0.01667 | I4: 0.01364 | J4: 0.01061 | K4: 0.00758 | L4: 0.00455 | M4: 0.00152
A5: 2 | B5: 0.03636 | C5: 0.03636 | D5: 0.03636 | E5: 0.03636 | F5: 0.03636 | G5: 0.03636 | H5: 0.03636 | I5: 0.03636 | J5: 0.03636 | K5: 0.03636 | L5: 0.03636 | M5: 0.03636
A6: 3 | B6: 0.03636 | C6: 0.03636 | D6: 0.03636 | E6: 0.03636 | F6: 0.03636 | G6: 0.03636 | H6: 0.03636 | I6: 0.03636 | J6: 0.03636 | K6: 0.03636 | L6: 0.03636 | M6: 0.03636
A7: 4 | B7: 0.03636 | C7: 0.03636 | D7: 0.03636 | E7: 0.03636 | F7: 0.03636 | G7: 0.03636 | H7: 0.03636 | I7: 0.03636 | J7: 0.03636 | K7: 0.03636 | L7: 0.03636 | M7: 0.03636
A8: 5 | B8: 0.03636 | C8: 0.03636 | D8: 0.03636 | E8: 0.03636 | F8: 0.03636 | G8: 0.03636 | H8: 0.03636 | I8: 0.03636 | J8: 0.03636 | K8: 0.03636 | L8: 0.03636 | M8: 0.03636
A9: 6 | B9: 0.03636 | C9: 0.03636 | D9: 0.03636 | E9: 0.03636 | F9: 0.03636 | G9: 0.03636 | H9: 0.03636 | I9: 0.03636 | J9: 0.03636 | K9: 0.03636 | L9: 0.03636 | M9: 0.03636
A10: 7 | B10: 0.03636 | C10: 0.03636 | D10: 0.03636 | E10: 0.03636 | F10: 0.03636 | G10: 0.03636 | H10: 0.03636 | I10: 0.03636 | J10: 0.03636 | K10: 0.03636 | L10: 0.03636 | M10: 0.03636
A11: 8 | B11: 0.03636 | C11: 0.03636 | D11: 0.03636 | E11: 0.03636 | F11: 0.03636 | G11: 0.03636 | H11: 0.03636 | I11: 0.03636 | J11: 0.03636 | K11: 0.03636 | L11: 0.03636 | M11: 0.03636
A12: 9 | B12: 0.03636 | C12: 0.03636 | D12: 0.03636 | E12: 0.03636 | F12: 0.03636 | G12: 0.03636 | H12: 0.03636 | I12: 0.03636 | J12: 0.03636 | K12: 0.03636 | L12: 0.03636 | M12: 0.03636
A13: 10 | B13: 0.03637 | C13: 0.03637 | D13: 0.03637 | E13: 0.03637 | F13: 0.03637 | G13: 0.03637 | H13: 0.03636 | I13: 0.03636 | J13: 0.03636 | K13: 0.03636 | L13: 0.03636 | M13: 0.03636
A14: 11 | B14: 0.03636 | C14: 0.03636 | D14: 0.03636 | E14: 0.03636 | F14: 0.03636 | G14: 0.03636 | H14: 0.03637 | I14: 0.03637 | J14: 0.03637 | K14: 0.03637 | L14: 0.03637 | M14: 0.03637
A15: 12 | B15: 0.03637 | C15: 0.03637 | D15: 0.03637 | E15: 0.03637 | F15: 0.03637 | G15: 0.03637 | H15: 0.03636 | I15: 0.03636 | J15: 0.03636 | K15: 0.03636 | L15: 0.03636 | M15: 0.03636
... A31: 28 | B31: 0.0197 | C31: 0.02273 | D31: 0.02576 | E31: 0.02879 | F31: 0.03182 | G31: 0.03485 | H31: 0.03636 | I31: 0.03636 | J31: 0.03636 | K31: 0.03636 | L31: 0.03636 | M31: 0.03636
A32: 29 | H32: 0.00152 | I32: 0.00455 | J32: 0.00758 | K32: 0.01061 | L32: 0.01364 | M32: 0.01667

Sheet 39-Year
A1: 39-Year Asset | B1: SL | O1: Mid-Month Convention
A2: Month In Service | B2: January | C2: February | D2: March | E2: April | F2: May | G2: June | H2: July | I2: August | J2: September | K2: October | L2: November | M2: December | O2: Nonresidential Rental Property
A3: Year No. | B3: 1 | C3: 2 | D3: 3 | E3: 4 | F3: 5 | G3: 6 | H3: 7 | I3: 8 | J3: 9 | K3: 10 | L3: 11 | M3: 12
A4: 1 | B4: 0.02461 | C4: 0.02247 | D4: 0.02033 | E4: 0.01819 | F4: 0.01605 | G4: 0.01391 | H4: 0.01177 | I4: 0.00963 | J4: 0.00749 | K4: 0.00535 | L4: 0.00321 | M4: 0.00107
A5: 2 | B5: 0.02564 | C5: 0.02564 | D5: 0.02564 | E5: 0.02564 | F5: 0.02564 | G5: 0.02564 | H5: 0.02564 | I5: 0.02564 | J5: 0.02564 | K5: 0.02564 | L5: 0.02564 | M5: 0.02564
A6: 3 | B6: 0.02564 | C6: 0.02564 | D6: 0.02564 | E6: 0.02564 | F6: 0.02564 | G6: 0.02564 | H6: 0.02564 | I6: 0.02564 | J6: 0.02564 | K6: 0.02564 | L6: 0.02564 | M6: 0.02564
A7: 4 | B7: 0.02564 | C7: 0.02564 | D7: 0.02564 | E7: 0.02564 | F7: 0.02564 | G7: 0.02564 | H7: 0.02564 | I7: 0.02564 | J7: 0.02564 | K7: 0.02564 | L7: 0.02564 | M7: 0.02564
A8: 5 | B8: 0.02564 | C8: 0.02564 | D8: 0.02564 | E8: 0.02564 | F8: 0.02564 | G8: 0.02564 | H8: 0.02564 | I8: 0.02564 | J8: 0.02564 | K8: 0.02564 | L8: 0.02564 | M8: 0.02564
A9: 6 | B9: 0.02564 | C9: 0.02564 | D9: 0.02564 | E9: 0.02564 | F9: 0.02564 | G9: 0.02564 | H9: 0.02564 | I9: 0.02564 | J9: 0.02564 | K9: 0.02564 | L9: 0.02564 | M9: 0.02564
A10: 7 | B10: 0.02564 | C10: 0.02564 | D10: 0.02564 | E10: 0.02564 | F10: 0.02564 | G10: 0.02564 | H10: 0.02564 | I10: 0.02564 | J10: 0.02564 | K10: 0.02564 | L10: 0.02564 | M10: 0.02564
A11: 8 | B11: 0.02564 | C11: 0.02564 | D11: 0.02564 | E11: 0.02564 | F11: 0.02564 | G11: 0.02564 | H11: 0.02564 | I11: 0.02564 | J11: 0.02564 | K11: 0.02564 | L11: 0.02564 | M11: 0.02564
A12: 9 | B12: 0.02564 | C12: 0.02564 | D12: 0.02564 | E12: 0.02564 | F12: 0.02564 | G12: 0.02564 | H12: 0.02564 | I12: 0.02564 | J12: 0.02564 | K12: 0.02564 | L12: 0.02564 | M12: 0.02564
A13: 10 | B13: 0.02564 | C13: 0.02564 | D13: 0.02564 | E13: 0.02564 | F13: 0.02564 | G13: 0.02564 | H13: 0.02564 | I13: 0.02564 | J13: 0.02564 | K13: 0.02564 | L13: 0.02564 | M13: 0.02564
A14: 11 | B14: 0.02564 | C14: 0.02564 | D14: 0.02564 | E14: 0.02564 | F14: 0.02564 | G14: 0.02564 | H14: 0.02564 | I14: 0.02564 | J14: 0.02564 | K14: 0.02564 | L14: 0.02564 | M14: 0.02564
A15: 12 | B15: 0.02564 | C15: 0.02564 | D15: 0.02564 | E15: 0.02564 | F15: 0.02564 | G15: 0.02564 | H15: 0.02564 | I15: 0.02564 | J15: 0.02564 | K15: 0.02564 | L15: 0.02564 | M15: 0.02564
... A43: 40 | B43: 0.00107 | C43: 0.00321 | D43: 0.00535 | E43: 0.00749 | F43: 0.00963 | G43: 0.01177 | H43: 0.01391 | I43: 0.01605 | J43: 0.01819 | K43: 0.02033 | L43: 0.02247 | M43: 0.02461

Sheet 5,7,15-Year
A1: 5-Year Asset | B1: 200 DB | AA1: Convention | AC1: Yes / No
A2: Convention | B2: Half-Year | C2: Mid-Qtr (Q1) | D2: Mid-Qtr (Q2) | E2: Mid-Qtr (Q3) | F2: Mid-Qtr (Q4) | AA2: -- | AC2: --
A3: 1 | B3: 0.2 | C3: 0.35 | D3: 0.25 | E3: 0.15 | F3: 0.05 | AA3: Half-Year | AC3: Yes
A4: 2 | B4: 0.32 | C4: 0.26 | D4: 0.3 | E4: 0.34 | F4: 0.38 | AA4: Mid-Qtr (Q1) | AC4: No
A5: 3 | B5: 0.192 | C5: 0.156 | D5: 0.18 | E5: 0.204 | F5: 0.228 | AA5: Mid-Qtr (Q2)
A6: 4 | B6: 0.1152 | C6: 0.1101 | D6: 0.1137 | E6: 0.1224 | F6: 0.1368 | AA6: Mid-Qtr (Q3)
A7: 5 | B7: 0.1152 | C7: 0.1101 | D7: 0.1137 | E7: 0.113 | F7: 0.1094 | AA7: Mid-Qtr (Q4)
A8: 6 | B8: 0.0576 | C8: 0.0138 | D8: 0.0426 | E8: 0.0706 | F8: 0.0958
A11: 7-Year Asset | B11: 200 DB
A12: Convention | B12: Half-Year | C12: Mid-Qtr (Q1) | D12: Mid-Qtr (Q2) | E12: Mid-Qtr (Q3) | F12: Mid-Qtr (Q4)
A13: 1 | B13: 0.1429 | C13: 0.25 | D13: 0.1785 | E13: 0.1071 | F13: 0.0357
A14: 2 | B14: 0.2449 | C14: 0.2143 | D14: 0.2347 | E14: 0.2551 | F14: 0.2755
A15: 3 | B15: 0.1749 | C15: 0.1531 | D15: 0.1676 | E15: 0.1822 | F15: 0.1968
A16: 4 | B16: 0.1249 | C16: 0.1093 | D16: 0.1197 | E16: 0.1302 | F16: 0.1406
A17: 5 | B17: 0.0893 | C17: 0.0875 | D17: 0.0887 | E17: 0.093 | F17: 0.1004
A18: 6 | B18: 0.0892 | C18: 0.0874 | D18: 0.0887 | E18: 0.0885 | F18: 0.0873
A19: 7 | B19: 0.0893 | C19: 0.0875 | D19: 0.0887 | E19: 0.0886 | F19: 0.0873
A20: 8 | B20: 0.0446 | C20: 0.0109 | D20: 0.0334 | E20: 0.0553 | F20: 0.0764
A23: 15-Year Asset | B23: 150 DB | F23: Page 180
A24: Convention | B24: Half-Year | C24: Mid-Qtr (Q1) | D24: Mid-Qtr (Q2) | E24: Mid-Qtr (Q3) | F24: Mid-Qtr (Q4)
A25: 1 | B25: 0.05 | C25: 0.0875 | D25: 0.0625 | E25: 0.0375 | F25: 0.0125
A26: 2 | B26: 0.095 | C26: 0.0913 | D26: 0.0938 | E26: 0.0963 | F26: 0.0988
A27: 3 | B27: 0.0855 | C27: 0.0821 | D27: 0.0844 | E27: 0.0866 | F27: 0.0889
A28: 4 | B28: 0.077 | C28: 0.0739 | D28: 0.0759 | E28: 0.078 | F28: 0.08
A29: 5 | B29: 0.0693 | C29: 0.0665 | D29: 0.0683 | E29: 0.0702 | F29: 0.072
A30: 6 | B30: 0.0623 | C30: 0.0599 | D30: 0.0615 | E30: 0.0631 | F30: 0.0648
A31: 7 | B31: 0.059 | C31: 0.059 | D31: 0.0591 | E31: 0.059 | F31: 0.059
A32: 8 | B32: 0.059 | C32: 0.0591 | D32: 0.059 | E32: 0.059 | F32: 0.059
A33: 9 | B33: 0.0591 | C33: 0.059 | D33: 0.0591 | E33: 0.0591 | F33: 0.059
A34: 10 | B34: 0.059 | C34: 0.0591 | D34: 0.059 | E34: 0.059 | F34: 0.0591
A35: 11 | B35: 0.0591 | C35: 0.059 | D35: 0.0591 | E35: 0.0591 | F35: 0.059
A36: 12 | B36: 0.059 | C36: 0.0591 | D36: 0.059 | E36: 0.059 | F36: 0.0591
... A40: 16 | B40: 0.0295 | C40: 0.0074 | D40: 0.0221 | E40: 0.0369 | F40: 0.0517
